{"cote": "Avranches. Biblioth\u00e8que municipale Edouard Le H\u00e9richer, Ms. 72", "ark_portail": "ark:/43093/mdatad64a1b488e8b5b3f66105e86c4d47422b3a07818", "langue": "latin", "start_year": 1040, "stop_year": "", "notes_scopecontent": "", "manifest_url": "https://api.irht.cnrs.fr/ark:/63955/fkjf1cwh02my/manifest.json", "qid_data": "https://data.biblissima.fr/entity/Q204566", "files": [{"zones": [{"type": "MainZone", "lines": [{"type": "DefaultLine", "content": "diaud.esat u masaimt n", "wh": [1148, 53], "xy": [283, 0]}, {"type": "DefaultLine", "content": "replete terram. Insuper & iam come", "wh": [1167, 145], "xy": [284, 47]}, {"type": "DefaultLine", "content": "dendarum carnium licentia relaxa", "wh": [1182, 148], "xy": [280, 190]}, {"type": "DefaultLine", "content": "tur : & omne quod mouetur uobis", "wh": [1170, 145], "xy": [287, 333]}, {"type": "DefaultLine", "content": "erit in escam sicut holera herba", "wh": [1146, 145], "xy": [286, 472]}, {"type": "DefaultLine", "content": "rum dedi uobis uniuersa\u0303", "wh": [1004, 135], "xy": [285, 615]}, {"type": "DefaultLine", "content": "Currit ad abraham. ilaac. & ia cob.", "wh": [1192, 149], "xy": [245, 751]}, {"type": "DefaultLine", "content": "equibus prior trigamus. secundus", "wh": [1169, 158], "xy": [289, 893]}, {"type": "DefaultLine", "content": "monagamus. tertius quattuor", "wh": [1143, 143], "xy": [294, 1046]}, {"type": "DefaultLine", "content": "uxorum. e\u0303. lie\u0327. racel. bale\u0327. & zelphe\u0327.", "wh": [1219, 183], "xy": [295, 1157]}, {"type": "DefaultLine", "content": "& adseric abraham ob fide i", "wh": [1076, 143], "xy": [296, 1316]}, {"type": "DefaultLine", "content": "meritum benedictionem ingeneratio", "wh": [1143, 144], "xy": [298, 1461]}, {"type": "DefaultLine", "content": "nem filii suscepisse. laram intxpo", "wh": [1044, 161], "xy": [297, 1597]}, {"type": "DefaultLine", "content": "aecc\u0142iae cui defecerant muliebria.", "wh": [1138, 143], "xy": [290, 1744]}, {"type": "DefaultLine", "content": "maledictionem sterilitatis partus", "wh": [1114, 155], "xy": [301, 1880]}, {"type": "DefaultLine", "content": "benedictione mutasse. Quod rebecca", "wh": [1378, 159], "xy": [289, 2014]}, {"type": "DefaultLine", "content": "benedictione mutasse", "wh": [739, 146], "xy": [289, 2025]}, {"type": "DefaultLine", "content": "uod rebecca", "wh": [405, 160], "xy": [1116, 2017]}, {"type": "DefaultLine", "content": "ierit quasi \ua753phetes in terrogare", "wh": [1165, 161], "xy": [305, 2164]}, {"type": "DefaultLine", "content": "pnipippprperrsrrepereeppeppreeteeeeptrepes eretereri drrerireppertpresteretyrreisrri", "wh": [1666, 119], "xy": [1, 2297]}, {"type": "DefaultLine", "content": "umu ISSEEIONOSAU", "wh": [1042, 113], "xy": [625, 2386]}], "wh": [1337, 2400], "xy": [215, 3]}], "alto": "f0-f-4.xml", "wh": [1668, 2500]}, {"zones": [{"type": "MainZone", "lines": [{"type": "DefaultLine", "content": "AURAMEHES", "wh": [847, 95], "xy": [131, 0]}, {"type": "DefaultLine", "content": "audire blasphemias", "wh": [932, 239], "xy": [202, 117]}, {"type": "DefaultLine", "content": "RiMa inquit di\u0303 sententia est :", "wh": [1446, 193], "xy": [336, 367]}, {"type": "DefaultLine", "content": "Propter q\u0111 dimict& homo patrem", "wh": [1630, 192], "xy": [217, 548]}, {"type": "DefaultLine", "content": "& matrem suam & adherebit uxori", "wh": [1673, 190], "xy": [216, 730]}, {"type": "DefaultLine", "content": "suae : & erunt duo incarne una. Ac", "wh": [1572, 183], "xy": [211, 901]}, {"type": "DefaultLine", "content": "ne forsitan diceremus hoc scriptum", "wh": [1541, 198], "xy": [224, 1075]}, {"type": "DefaultLine", "content": "inueteri testam\u0303to. adserit adn\u0303o quoq\uf1ac", "wh": [1598, 191], "xy": [233, 1274]}, {"type": "DefaultLine", "content": "id ipsum in euangelio confirmariqd\u0303", "wh": [1567, 190], "xy": [237, 1455]}, {"type": "DefaultLine", "content": "ds\u0303 coniunxit: homo nonsepar&. Stati\u0303", "wh": [1633, 189], "xy": [215, 1631]}, {"type": "DefaultLine", "content": "q\uf1ac subnectit. Crescite & multiplicami", "wh": [1654, 187], "xy": [222, 1814]}, {"type": "DefaultLine", "content": "ni: & replete terram. Et per ordine\u0303", "wh": [1567, 189], "xy": [233, 1997]}, {"type": "DefaultLine", "content": "replicat. seth. enos. caiNati.", "wh": [1486, 196], "xy": [224, 2168]}, {"type": "DefaultLine", "content": "malaleel. iaret. enoch. matusalam", "wh": [1564, 153], "xy": [226, 2346]}], "wh": [1789, 2428], "xy": [155, 72]}, {"type": "MarginTextZone", "lines": [{"type": "DefaultLine", "content": "idibl. mua. \ua7512. E. 4", "wh": [1110, 149], "xy": [1131, 6]}], "wh": [1108, 144], "xy": [1128, 6]}, {"type": "MainZone", "lines": [{"type": "DefaultLine", "content": "dictio. crescite & multiplicam", "wh": [1199, 236], "xy": [2184, 156]}, {"type": "DefaultLine", "content": "replete terram: Insuper & ian", "wh": [1202, 198], "xy": [2181, 385]}, {"type": "DefaultLine", "content": "dendarum carnium licentia", "wh": [1217, 183], "xy": [2167, 571]}, {"type": "DefaultLine", "content": "tur : & omne quod mouetur", "wh": [1217, 180], "xy": [2167, 754]}, {"type": "DefaultLine", "content": "erit in escam sicut holera", "wh": [1213, 186], "xy": [2164, 925]}, {"type": "DefaultLine", "content": "rum dedi uobis uniuersa", "wh": [1224, 193], "xy": [2160, 1106]}, {"type": "DefaultLine", "content": "Currit ad abraham isaac. & i", "wh": [1283, 206], "xy": [2099, 1286]}, {"type": "DefaultLine", "content": "equibus prio\ua775 trigamus. sec", "wh": [1238, 207], "xy": [2147, 1467]}, {"type": "DefaultLine", "content": "monagamus. tertius quai", "wh": [1230, 187], "xy": [2153, 1658]}, {"type": "DefaultLine", "content": "uxorum. e\u0303. lie\u0327. racel. bale\u0327.o", "wh": [1231, 218], "xy": [2154, 1822]}, {"type": "DefaultLine", "content": "& adseric abraham ob fic", "wh": [1243, 188], "xy": [2142, 2014]}, {"type": "DefaultLine", "content": "meritum benedictionem inge", "wh": [1240, 185], "xy": [2144, 2194]}, {"type": "DefaultLine", "content": "nem filu suscepisse. Saram inte", "wh": [1260, 137], "xy": [2125, 2362]}], "wh": [1329, 2371], "xy": [2057, 129]}], "alto": "f1-f-4.xml", "wh": [3386, 2500]}, {"zones": [{"type": "MainZone", "lines": [{"type": "DefaultLine", "content": "Non lolum estimes te uicisse: uterq\uf1ac", "wh": [1204, 120], "xy": [175, 0]}, {"type": "DefaultLine", "content": "nostrum palmas refert. Tu mei.", "wh": [1142, 136], "xy": [248, 114]}, {"type": "DefaultLine", "content": "i i", "wh": [921, 34], "xy": [440, 0]}, {"type": "DefaultLine", "content": "& ego erioris. Utinamq\uf1ac sic sem\ua751", "wh": [1125, 149], "xy": [237, 248]}, {"type": "DefaultLine", "content": "michi disputare contingat: ut ad", "wh": [1120, 146], "xy": [247, 379]}, {"type": "DefaultLine", "content": "meliora proficiens. deseram quod", "wh": [1135, 151], "xy": [251, 511]}, {"type": "DefaultLine", "content": "male tenebam. Unum autem", "wh": [1141, 136], "xy": [246, 648]}, {"type": "DefaultLine", "content": "tibi confiteor : quia mores meoru\u0303", "wh": [1163, 141], "xy": [247, 778]}, {"type": "DefaultLine", "content": "ad prime\u0328 noui facilius eos uinci", "wh": [1111, 133], "xy": [238, 920]}, {"type": "DefaultLine", "content": "posse quam per suader", "wh": [791, 144], "xy": [241, 1052]}, {"type": "HeadingLine", "content": "UPERUE", "wh": [617, 149], "xy": [767, 1319]}, {"type": "HeadingLine", "content": "NIENTES", "wh": [672, 159], "xy": [800, 1459]}, {"type": "HeadingLine", "content": "EGIPTI", "wh": [546, 142], "xy": [825, 1602]}, {"type": "DefaultLine", "content": "qui ostenderent", "wh": [529, 144], "xy": [911, 2009]}, {"type": "DefaultLine", "content": "piuntiae \ua751magistrorum discip\u0142os", "wh": [1192, 199], "xy": [249, 2282]}, {"type": "HeadingLine", "content": "se antiquorum", "wh": [526, 146], "xy": [916, 2158]}], "wh": [1298, 2490], "xy": [178, 0]}, {"type": "MainZone", "lines": [{"type": "DefaultLine", "content": "q. pa", "wh": [167, 128], "xy": [1672, 12]}, {"type": "DefaultLine", "content": "tori", "wh": [165, 122], "xy": [1674, 148]}, {"type": "DefaultLine", "content": "quib", "wh": [162, 143], "xy": [1677, 399]}, {"type": "DefaultLine", "content": "est u", "wh": [169, 140], "xy": [1670, 663]}, {"type": "DefaultLine", "content": "Antec", "wh": [215, 142], "xy": [1624, 1599]}, {"type": "DefaultLine", "content": "uos", "wh": [140, 121], "xy": [1690, 1743]}, {"type": "DefaultLine", "content": "dicer", "wh": [157, 129], "xy": [1682, 1872]}, {"type": "DefaultLine", "content": "ARNE", "wh": [227, 150], "xy": [1611, 2156]}, {"type": "DefaultLine", "content": "plar", "wh": [160, 174], "xy": [1679, 2295]}], "wh": [228, 2473], "xy": [1612, 11]}], "alto": "f2-f-126v.xml", "wh": [1840, 2500]}, {"zones": [{"type": "MainZone", "lines": [{"type": "HeadingLine", "content": "INCIPIT PRAE", "wh": [1569, 300], "xy": [499, 196]}, {"type": "HeadingLine", "content": "FAELO. AURE", "wh": [1604, 280], "xy": [521, 555]}, {"type": "HeadingLine", "content": "LIT AUGUS", "wh": [1460, 304], "xy": [513, 899]}, {"type": "HeadingLine", "content": "TINI INEPLA", "wh": [1655, 328], "xy": [532, 1254]}, {"type": "HeadingLine", "content": "AD GALA", "wh": [1515, 316], "xy": [529, 1643]}], "wh": [1772, 2363], "xy": [445, 137]}, {"type": "MarginTextZone", "lines": [{"type": "DefaultLine", "content": "Diblmnuai. E2.F. \u204a 9o", "wh": [1190, 143], "xy": [1149, 0]}], "wh": [1197, 139], "xy": [1143, 0]}, {"type": "MainZone", "lines": [{"type": "DefaultLine", "content": "qui dam excircum ci", "wh": [915, 190], "xy": [2497, 103]}, {"type": "DefaultLine", "content": "xp\u0303i\u0303ani nomine none", "wh": [905, 203], "xy": [2508, 273]}, {"type": "DefaultLine", "content": "tenentes ipsum gra\u0303e", "wh": [911, 196], "xy": [2502, 452]}, {"type": "DefaultLine", "content": "& adhuc uolentes es", "wh": [918, 188], "xy": [2495, 624]}, {"type": "DefaultLine", "content": "legis. quae dn\u0303s ds\u0303 in", "wh": [918, 215], "xy": [2495, 796]}, {"type": "DefaultLine", "content": "non iusticiae seruier", "wh": [904, 182], "xy": [2509, 999]}, {"type": "DefaultLine", "content": "to. iustam scilic& li", "wh": [952, 207], "xy": [2461, 1175]}, {"type": "DefaultLine", "content": "hominibus dando. a", "wh": [922, 192], "xy": [2490, 1370]}, {"type": "DefaultLine", "content": "peccata eorum non.", "wh": [922, 180], "xy": [2491, 1567]}, {"type": "DefaultLine", "content": "Non enim aufert pec", "wh": [993, 221], "xy": [2420, 1733]}, {"type": "DefaultLine", "content": "fidei : quae perdilecr", "wh": [923, 190], "xy": [2489, 1934]}, {"type": "DefaultLine", "content": "Subhac gra ergo iam", "wh": [996, 219], "xy": [2417, 2110]}, {"type": "DefaultLine", "content": "stitutos. illi uolebant", "wh": [931, 175], "xy": [2482, 2305]}], "wh": [1041, 2406], "xy": [2373, 87]}], "alto": "f3-f-150.xml", "wh": [3414, 2500]}, {"zones": [{"type": "MainZone", "lines": [{"type": "DefaultLine", "content": "PSAMANUS UIUAT. QUAE", "wh": [1029, 156], "xy": [433, 222]}, {"type": "HeadingLine", "content": "TAM BENE SCRIBERE CURAT", "wh": [1021, 149], "xy": [433, 356]}, {"type": "HeadingLine", "content": "SIaUIS SrT SCRIETOR", "wh": [864, 140], "xy": [347, 613]}, {"type": "HeadingLine", "content": "IUIERIS COGNOSCERE LECIOR", "wh": [1086, 140], "xy": [453, 747]}, {"type": "HeadingLine", "content": "HUNC STUDUIT TOTUM.", "wh": [1043, 129], "xy": [342, 1021]}, {"type": "HeadingLine", "content": "FROTMUNDUS SCRIBERE LIBROM", "wh": [1156, 140], "xy": [454, 1137]}, {"type": "HeadingLine", "content": "OUCILA CONSCRIESIT", "wh": [921, 125], "xy": [331, 1408]}, {"type": "DefaultLine", "content": "IUAPLURIUA SCAPEA EGIT", "wh": [974, 151], "xy": [468, 1539]}, {"type": "DefaultLine", "content": "FELIX FROT MUNDUS.", "wh": [837, 140], "xy": [383, 1813]}, {"type": "HeadingLine", "content": "PERSCLA FRMIER AMANDUS", "wh": [993, 148], "xy": [458, 1953]}], "wh": [1365, 1993], "xy": [289, 184]}], "alto": "f4-f-199v.xml", "wh": [1798, 2500]}]}