{"cote": "Paris. Biblioth\u00e8que nationale de France, D\u00e9partement des manuscrits, Latin 3202", "ark_portail": "ark:/43093/mdatabcc6df30f25139286ae4e4014ca522a15b6889c5", "langue": "lat", "start_year": 1501, "stop_year": "", "notes_scopecontent": "", "manifest_url": "https://api.irht.cnrs.fr/ark:/63955/fjumzcafnb1g/manifest.json", "qid_data": "https://data.biblissima.fr/entity/Q109842", "files": [{"zones": [{"type": "MainZone", "lines": [{"type": "DefaultLine", "content": "Questiones miscelsainx \ua751 fre\u0303s", "wh": [1657, 142], "xy": [112, 0]}, {"type": "DefaultLine", "content": "e sc \u00b6sid oso", "wh": [917, 31], "xy": [899, 0]}, {"type": "DefaultLine", "content": "hri stophox menhzmger et Nicolau", "wh": [1699, 170], "xy": [117, 127]}, {"type": "DefaultLine", "content": "Illenbog alternatim \ua76fscrixte i\u0303cix", "wh": [1720, 182], "xy": [96, 271]}, {"type": "DefaultLine", "content": "i\u0303 cix", "wh": [176, 158], "xy": [1640, 294]}, {"type": "DefaultLine", "content": "frliciter / i\u0303 caxi\u0303te anui", "wh": [1186, 166], "xy": [325, 422]}, {"type": "DefaultLine", "content": "ratu\u0303 corpus quod i\u0303 resurestione ha", "wh": [1645, 146], "xy": [53, 681]}, {"type": "DefaultLine", "content": "Cuestio pri\u0303ma", "wh": [895, 145], "xy": [439, 561]}, {"type": "DefaultLine", "content": "n\u0303 plicitate\u0303 spta cedat. ut tot\ua770 homo", "wh": [1646, 155], "xy": [77, 805]}, {"type": "DefaultLine", "content": "n ita fut\u1dd1 u\u0303 sit spirstuale corp\ua770", "wh": [1605, 153], "xy": [88, 926]}, {"type": "DefaultLine", "content": "ile\u0303 q\u0363nda\u0303 fatilitate\u0303 spiritale dica", "wh": [1660, 173], "xy": [65, 1062]}, {"type": "DefaultLine", "content": "bstantia\u0303 corpor alem. Nico.", "wh": [1664, 173], "xy": [112, 1203]}, {"type": "DefaultLine", "content": "ilerte \ua76ffeater Christoyhore", "wh": [1244, 164], "xy": [422, 1370]}, {"type": "DefaultLine", "content": "no\u0303 te latet qr \ua753 i\u0303genqi exerti", "wh": [1307, 158], "xy": [412, 1508]}, {"type": "DefaultLine", "content": "tato\u0303e et cultura \ua76fuenerit int", "wh": [1333, 144], "xy": [417, 1634]}, {"type": "DefaultLine", "content": "nos ut uicissim mutuas nobis", "wh": [1350, 146], "xy": [416, 1754]}, {"type": "DefaultLine", "content": "\ua753ponam\ua770 questiones enoda\u0303das", "wh": [1352, 150], "xy": [416, 1876]}, {"type": "DefaultLine", "content": "tlabe\u0303s\u0303q\uf1ac i\u0303 hac re abbe ur\u0303i as", "wh": [1328, 162], "xy": [411, 1991]}, {"type": "DefaultLine", "content": "sensu\u0303. x\u0365mo dm\u0303i i\u0303taq\uf1ac caue\u0303du\u0303", "wh": [1303, 151], "xy": [421, 2123]}, {"type": "DefaultLine", "content": "nobis e\u0303 ne \ua751 dissidiu\u0303 simulta", "wh": [1333, 154], "xy": [420, 2250]}, {"type": "DefaultLine", "content": "te\u0303q\uf1ac qua\u0303tu\u0303q\uf1ac aut certe \ua751 in", "wh": [1291, 119], "xy": [424, 2380]}], "wh": [1797, 2494], "xy": [6, 2]}], "alto": "f0-f-169.xml", "wh": [1817, 2500]}]}