{"cote": "Orl\u00e9ans. M\u00e9diath\u00e8que, MS 37", "ark_portail": "ark:/43093/mdataf8f75141869483f56fa1e2c65030e2b9603445d7", "langue": "latin", "start_year": 1201, "stop_year": "", "notes_scopecontent": "", "manifest_url": "https://api.irht.cnrs.fr/ark:/63955/fbyhnqhbl10m/manifest.json", "qid_data": "https://data.biblissima.fr/entity/Q206254", "files": [{"zones": [{"type": "text", "lines": [{"type": "DefaultLine", "content": "losue", "wh": [50, 44], "xy": [278, 365]}], "wh": [0, 0], "xy": [0, 0]}, {"type": "MainZone", "lines": [{"type": "HeadingLine", "content": "\u204aelimus saceritatis", "wh": [219, 44], "xy": [369, 542]}, {"type": "DefaultLine", "content": "orima \u204a iu\u033eitis. \u204a sunt", "wh": [223, 37], "xy": [367, 577]}, {"type": "DefaultLine", "content": "fructus terreune i\u0303 ecclia", "wh": [227, 35], "xy": [366, 603]}, {"type": "DefaultLine", "content": "tricesimus. sengesimus", "wh": [226, 35], "xy": [365, 629]}, {"type": "DefaultLine", "content": "centesimus. martires .s.", "wh": [229, 37], "xy": [362, 655]}, {"type": "DefaultLine", "content": "uidue. uirgines. \u204a multi", "wh": [234, 36], "xy": [361, 683]}, {"type": "DefaultLine", "content": "plicantur sen ist\u0142. exhus", "wh": [239, 40], "xy": [356, 709]}, {"type": "DefaultLine", "content": "qui non ex sangunibus", "wh": [236, 36], "xy": [356, 739]}, {"type": "DefaultLine", "content": "u\uf1ac exuo .s.n. eruo .iii. s\uf1ac", "wh": [242, 38], "xy": [353, 766]}, {"type": "DefaultLine", "content": "ex deo nati sunt. \u204a filu dei", "wh": [238, 34], "xy": [353, 795]}, {"type": "DefaultLine", "content": "qui dispersi erant \ua76fgrega", "wh": [240, 42], "xy": [354, 819]}, {"type": "DefaultLine", "content": "tur inunu\u0303 sabbatizat", "wh": [234, 35], "xy": [355, 850]}, {"type": "DefaultLine", "content": "pp\u0142s d\u033ei n\u0303 acorui\u0303sione co\u0303", "wh": [234, 43], "xy": [354, 875]}, {"type": "DefaultLine", "content": "uiuni s\uf1ac abopere peccati.", "wh": [239, 40], "xy": [353, 906]}, {"type": "DefaultLine", "content": "defiuictus est ergo moy", "wh": [233, 43], "xy": [352, 934]}, {"type": "DefaultLine", "content": "ses famurius der. deuiq i\u0303", "wh": [240, 42], "xy": [352, 966]}, {"type": "DefaultLine", "content": "isbello quodam licet i\u0303 ca", "wh": [241, 43], "xy": [352, 994]}, {"type": "DefaultLine", "content": "none uo\u0303 halratur miste", "wh": [245, 41], "xy": [352, 1025]}, {"type": "DefaultLine", "content": "rii huius figura describi", "wh": [235, 40], "xy": [352, 1054]}, {"type": "DefaultLine", "content": "t\u1dd1. Refertur enim qr duo", "wh": [237, 39], "xy": [352, 1082]}, {"type": "DefaultLine", "content": "moyses uidelant\u1dd1. unus", "wh": [238, 41], "xy": [350, 1110]}, {"type": "DefaultLine", "content": "uluens inspu \u204a alius mor", "wh": [250, 37], "xy": [353, 1141]}, {"type": "DefaultLine", "content": "tuus in corpore. litt\u0303a enim", "wh": [251, 41], "xy": [350, 1169]}, {"type": "DefaultLine", "content": "legis inanss\u204a uacua. ab", "wh": [239, 37], "xy": [351, 1201]}, {"type": "DefaultLine", "content": "om\u0303ib\uf1ac supaidictis. moy", "wh": [238, 43], "xy": [349, 1227]}, {"type": "DefaultLine", "content": "ses mortiuis incorpore. iii", "wh": [244, 37], "xy": [349, 1260]}, {"type": "DefaultLine", "content": "teuectus no legis spualis", "wh": [245, 45], "xy": [346, 1287]}, {"type": "DefaultLine", "content": "moyses e\u0303qui uiit i\u0303spu", "wh": [238, 37], "xy": [346, 1321]}, {"type": "DefaultLine", "content": "Alugustinus. Sicut", "wh": [239, 42], "xy": [344, 1375]}, {"type": "DefaultLine", "content": "fui cuiumoyse ero tecu\u0303", "wh": [241, 43], "xy": [346, 1404]}, {"type": "DefaultLine", "content": "Toc testimonio \u204a alus \ua753", "wh": [243, 38], "xy": [345, 1437]}, {"type": "DefaultLine", "content": "batur moyses de functus", "wh": [240, 43], "xy": [344, 1465]}, {"type": "DefaultLine", "content": "ut dei fonuilus \u204a deo pla", "wh": [238, 36], "xy": [345, 1498]}, {"type": "DefaultLine", "content": "cens cuiauis uieo illa", "wh": [253, 42], "xy": [345, 1524]}, {"type": "DefaultLine", "content": "dicta completa sit qd\u0303 no\u0303", "wh": [243, 36], "xy": [346, 1555]}, {"type": "DefaultLine", "content": "int\u033era\u0303 \ua753missionis intrau\u033eit", "wh": [253, 44], "xy": [346, 1580]}, {"type": "DefaultLine", "content": "exc\u0366 dautr incelligi d\u0303m in", "wh": [252, 38], "xy": [341, 1613]}, {"type": "DefaultLine", "content": "bonicerius suis aliq\u0363te\u0303po", "wh": [250, 45], "xy": [341, 1638]}, {"type": "DefaultLine", "content": "ralite uindicare. et tam\u0303", "wh": [245, 38], "xy": [341, 1670]}, {"type": "DefaultLine", "content": "eos i\u0303tir uasa honesta \u204a uti", "wh": [248, 49], "xy": [341, 1698]}, {"type": "DefaultLine", "content": "ua hsere.", "wh": [113, 54], "xy": [343, 1733]}], "wh": [266, 1242], "xy": [338, 534]}, {"type": "MainZone", "lines": [{"type": "DefaultLine", "content": "tri uob\u0303 t\u0363dam. Si", "wh": [241, 56], "xy": [611, 1389]}], "wh": [280, 1237], "xy": [606, 531]}, {"type": "MainZone", "lines": [{"type": "DefaultLine", "content": "t fac", "wh": [77, 59], "xy": [775, 526]}, {"type": "DefaultLine", "content": "OR. Nunc ergo exurgen", "wh": [326, 63], "xy": [871, 516]}, {"type": "DefaultLine", "content": "transiordanem hune \u204ac. ui", "wh": [314, 41], "xy": [873, 563]}, {"type": "DefaultLine", "content": "tum", "wh": [83, 59], "xy": [774, 581]}, {"type": "DefaultLine", "content": "de quomodo minister moy", "wh": [312, 40], "xy": [873, 591]}, {"type": "DefaultLine", "content": "si fuerit ihesus filius dei cu\u0303", "wh": [313, 43], "xy": [870, 617]}, {"type": "DefaultLine", "content": "est", "wh": [68, 58], "xy": [777, 637]}, {"type": "DefaultLine", "content": "uenit plenitudo temporis", "wh": [310, 43], "xy": [869, 645]}, {"type": "DefaultLine", "content": "misit deus filium sium fac", "wh": [318, 41], "xy": [871, 674]}, {"type": "DefaultLine", "content": "post", "wh": [71, 61], "xy": [781, 689]}, {"type": "DefaultLine", "content": "tum ex muliere factum sub", "wh": [309, 39], "xy": [871, 704]}, {"type": "DefaultLine", "content": "mor", "wh": [75, 60], "xy": [778, 746]}, {"type": "DefaultLine", "content": "lege. quia factus est sub le", "wh": [319, 40], "xy": [874, 732]}, {"type": "DefaultLine", "content": "ge moysi. factus est minister", "wh": [322, 42], "xy": [871, 761]}, {"type": "DefaultLine", "content": "moys.", "wh": [316, 35], "xy": [874, 789]}, {"type": "DefaultLine", "content": "moysi.", "wh": [178, 40], "xy": [873, 791]}, {"type": "HeadingLine", "content": "tem moysi serui", "wh": [236, 59], "xy": [617, 807]}, {"type": "DefaultLine", "content": "moysi.", "wh": [82, 42], "xy": [872, 792]}, {"type": "DefaultLine", "content": "\u00b6 pater.", "wh": [78, 38], "xy": [859, 843]}, {"type": "DefaultLine", "content": "\u00b6 ih\u0303m dei. filium.", "wh": [203, 39], "xy": [953, 839]}, {"type": "DefaultLine", "content": "deiut loqueretur dominus ad iosue filiu\u0303", "wh": [582, 57], "xy": [610, 862]}, {"type": "DefaultLine", "content": "q\u0365 quia u\u0303 uenit soluere legem s\uf1ac adiplere\u0303", "wh": [334, 36], "xy": [689, 902]}, {"type": "DefaultLine", "content": "nun ministrum moysi. et diceret ei.", "wh": [553, 66], "xy": [614, 914]}, {"type": "DefaultLine", "content": "\u00b6 Lex q\u0303 inq\u0363m pedagogns fuit. q Sidi\u0303i litteram. uiuit u\u0303", "wh": [511, 51], "xy": [670, 960]}, {"type": "DefaultLine", "content": "Loyses seruus meus mortuus est.", "wh": [558, 72], "xy": [616, 997]}, {"type": "DefaultLine", "content": "surge et transi iordanem istum tu et", "wh": [553, 63], "xy": [616, 1062]}, {"type": "DefaultLine", "content": "\u00b6 uiuentium ui\u0303 mitet qim\u0303 ip\u0303r posside", "wh": [317, 41], "xy": [870, 1100]}, {"type": "HeadingLine", "content": "omnis ppls tecu\u0303 interra l q\u0303 non uoyser q\u0303 uor", "wh": [589, 56], "xy": [615, 1125]}, {"type": "DefaultLine", "content": "bunt terram", "wh": [105, 43], "xy": [615, 1169]}, {"type": "HeadingLine", "content": "quam ego da", "wh": [211, 50], "xy": [986, 1156]}, {"type": "DefaultLine", "content": "tuo moyse", "wh": [100, 32], "xy": [612, 1195]}, {"type": "HeadingLine", "content": "q\u0365 qui sursum est.", "wh": [170, 36], "xy": [991, 1192]}, {"type": "DefaultLine", "content": "bo fillus israei.", "wh": [227, 63], "xy": [613, 1208]}, {"type": "DefaultLine", "content": "mnem locum quem", "wh": [308, 59], "xy": [890, 1212]}, {"type": "InterlinearLine", "content": "q qd la", "wh": [77, 33], "xy": [771, 1256]}, {"type": "DefaultLine", "content": "calcauerit uesti", "wh": [245, 60], "xy": [613, 1272]}, {"type": "DefaultLine", "content": "OR\ua775. Omne locu\u0303 qu\u0303ecu\u0303q\uf1ac ascen", "wh": [313, 46], "xy": [879, 1279]}, {"type": "InterlinearLine", "content": "uit ih\u0303c", "wh": [67, 31], "xy": [616, 1319]}, {"type": "DefaultLine", "content": "gllim pedisues", "wh": [241, 67], "xy": [613, 1325]}, {"type": "DefaultLine", "content": "deritis nestigiis pedu\u0303 ur\u0303o\ua775 uob\u033e", "wh": [308, 40], "xy": [876, 1315]}, {"type": "DefaultLine", "content": "dabo \u204a c\u0303. littera egis humi posita", "wh": [318, 37], "xy": [873, 1346]}, {"type": "DefaultLine", "content": "\u00b6uuii", "wh": [51, 33], "xy": [796, 1375]}, {"type": "DefaultLine", "content": "e\u0303 \u204a deorsum. n\u0303 g\u0366 ascenclit quilitt\u033eam", "wh": [334, 40], "xy": [872, 1374]}, {"type": "DefaultLine", "content": "legis sequitur sz si ascenderis ad", "wh": [314, 38], "xy": [872, 1404]}, {"type": "DefaultLine", "content": "ego sum islit i minister mens", "wh": [239, 38], "xy": [615, 1438]}, {"type": "DefaultLine", "content": "sp\u0303m delitta ascenclis locum exte", "wh": [322, 40], "xy": [871, 1431]}, {"type": "DefaultLine", "content": "ent.", "wh": [54, 34], "xy": [619, 1465]}, {"type": "DefaultLine", "content": "cut locutus sum", "wh": [220, 52], "xy": [617, 1477]}, {"type": "DefaultLine", "content": "sum \ua759\u0303 adeo in helitate accipies", "wh": [323, 44], "xy": [870, 1458]}, {"type": "DefaultLine", "content": "Sienum inhus q\u0303 scripta su\u0303t in", "wh": [322, 43], "xy": [869, 1488]}, {"type": "DefaultLine", "content": "\u00b6 Rab\u033e. letabiturde", "wh": [158, 40], "xy": [698, 1518]}, {"type": "DefaultLine", "content": "telligas formas e\u0303e\u0303 telestium \u204a q\u0303ra", "wh": [330, 44], "xy": [873, 1516]}, {"type": "DefaultLine", "content": "serta \u204a inuia. \u204a c\u0303. \u204a alibi. mul", "wh": [237, 34], "xy": [620, 1548]}, {"type": "DefaultLine", "content": "q\u0303 suisu\u0303 su\u0303t. ubi xp\u0303 e\u0303indext\u033ea dei se", "wh": [331, 40], "xy": [875, 1547]}, {"type": "DefaultLine", "content": "moysi adeserto \u204a", "wh": [236, 47], "xy": [617, 1571]}, {"type": "DefaultLine", "content": "deus. tunc illu\u0303 locu\u0303 in heditate as", "wh": [322, 42], "xy": [875, 1577]}, {"type": "DefaultLine", "content": "ti ulu deserte mag q\u0363m euis", "wh": [233, 34], "xy": [617, 1608]}, {"type": "DefaultLine", "content": "cipies. qr isbi xp\u0303c e\u0303 ibi\u204a minister", "wh": [323, 42], "xy": [878, 1605]}, {"type": "DefaultLine", "content": "lsbano lsq\uf1ac ad flu", "wh": [253, 53], "xy": [613, 1628]}, {"type": "DefaultLine", "content": "ei\ua770 Si g\u0366 usc\uf1ac ad ip\u0303m sedente\u0303 i\u0303 dexta\u0303 di\u0303", "wh": [340, 43], "xy": [876, 1635]}, {"type": "DefaultLine", "content": "\ua751ueni\u0303sfide u\u0365tute pitate \u204a ur uesti", "wh": [326, 42], "xy": [878, 1667]}, {"type": "DefaultLine", "content": "uium magnum", "wh": [236, 52], "xy": [613, 1687]}, {"type": "DefaultLine", "content": "gus q\u0303 lauit ilr x\u0368 ad uiu\u0303 locu\u0303 accesse.", "wh": [338, 48], "xy": [877, 1695]}, {"type": "DefaultLine", "content": "ris dabit t\u0365 d\u033es li no solum efficiarie heres d\u033ei s\uf1ac co\u0303leres xp\u0303i", "wh": [507, 57], "xy": [608, 1728]}], "wh": [616, 1260], "xy": [612, 510]}], "alto": "f0-p-005-vue-1.xml", "wh": [1689, 2499]}, {"zones": [{"type": "text", "lines": [{"type": "DefaultLine", "content": "Iosue", "wh": [49, 47], "xy": [272, 377]}], "wh": [0, 0], "xy": [0, 0]}, {"type": "MainZone", "lines": [{"type": "HeadingLine", "content": "\u204a eclimus siceritatis", "wh": [222, 53], "xy": [359, 549]}, {"type": "HeadingLine", "content": "orima \u204a u\u033estis. \u204a sunt", "wh": [228, 36], "xy": [358, 592]}, {"type": "DefaultLine", "content": "fructus terre une i\u0303 scclia.", "wh": [226, 35], "xy": [360, 617]}, {"type": "HeadingLine", "content": "tricesimus. seagesimus.", "wh": [223, 34], "xy": [361, 644]}, {"type": "DefaultLine", "content": "centesinuis. nartires .s.", "wh": [227, 37], "xy": [357, 668]}, {"type": "DefaultLine", "content": "uilue. uirgines. \u204a multi", "wh": [229, 36], "xy": [358, 696]}, {"type": "HeadingLine", "content": "plicantur sem\u0303 isr\u0142. ex hus", "wh": [234, 39], "xy": [353, 722]}, {"type": "DefaultLine", "content": "qui non ex sanguinibus", "wh": [229, 36], "xy": [354, 752]}, {"type": "DefaultLine", "content": "l\uf1ac exuo .c. n exuo .iii. s\uf1ac", "wh": [238, 40], "xy": [352, 778]}, {"type": "HeadingLine", "content": "ex deo nati sunt. \u204a filu dei", "wh": [235, 33], "xy": [350, 808]}, {"type": "DefaultLine", "content": "qui dispersi erant \ua76fgrega", "wh": [238, 41], "xy": [348, 833]}, {"type": "HeadingLine", "content": "tur inunu\u0303 sabbatirat", "wh": [227, 33], "xy": [351, 864]}, {"type": "DefaultLine", "content": "pp\u0142s d\u033ei n\u0303 acoruisione co\u0303", "wh": [230, 43], "xy": [349, 887]}, {"type": "DefaultLine", "content": "niuni s\uf1ac ab opere peccati.", "wh": [234, 39], "xy": [348, 918]}, {"type": "HeadingLine", "content": "defuuictus est ergo moy", "wh": [226, 40], "xy": [349, 948]}, {"type": "HeadingLine", "content": "ses famirius dei. deiu\ua759 i\u0303", "wh": [235, 38], "xy": [348, 978]}, {"type": "HeadingLine", "content": "ubello quodam licet i\u0303 ca", "wh": [237, 41], "xy": [348, 1006]}, {"type": "DefaultLine", "content": "none uo\u0303 habeatut miste", "wh": [241, 37], "xy": [348, 1037]}, {"type": "HeadingLine", "content": "ril huius figura describi", "wh": [233, 39], "xy": [348, 1064]}, {"type": "DefaultLine", "content": "t\u1dd1. Refertur auni qr duo", "wh": [237, 38], "xy": [347, 1094]}, {"type": "DefaultLine", "content": "moyses uidellint\u1dd1. unus", "wh": [234, 41], "xy": [348, 1121]}, {"type": "DefaultLine", "content": "uiuens in spu \u204a alius mor", "wh": [246, 38], "xy": [347, 1153]}, {"type": "HeadingLine", "content": "tuus in corpore. litt\u0303a euim", "wh": [250, 40], "xy": [346, 1181]}, {"type": "DefaultLine", "content": "legis inanis\u204a uacua. ab", "wh": [235, 35], "xy": [346, 1213]}, {"type": "HeadingLine", "content": "om\u0303ib\uf1ac supridictis. moy", "wh": [237, 40], "xy": [345, 1238]}, {"type": "DefaultLine", "content": "ses mortis incorpore. in", "wh": [244, 35], "xy": [343, 1272]}, {"type": "DefaultLine", "content": "teuectus no legis spualis", "wh": [244, 41], "xy": [341, 1299]}, {"type": "DefaultLine", "content": "moyses e\u0303qui uunt i\u0303sp\u0303u.", "wh": [239, 36], "xy": [343, 1331]}, {"type": "DefaultLine", "content": "Augustinus. Sicut", "wh": [237, 39], "xy": [339, 1387]}, {"type": "DefaultLine", "content": "fui cum moyse ero tecu\u0303", "wh": [241, 41], "xy": [341, 1414]}, {"type": "HeadingLine", "content": "\u204ahxc testimonio \u204a alus \ua753", "wh": [243, 36], "xy": [340, 1447]}, {"type": "HeadingLine", "content": "batur moyses defunctus", "wh": [241, 41], "xy": [341, 1473]}, {"type": "DefaultLine", "content": "ut dei fanuilus \u204adeo pla", "wh": [243, 37], "xy": [340, 1506]}, {"type": "DefaultLine", "content": "ceus cuauis meo illa uin", "wh": [256, 39], "xy": [338, 1534]}, {"type": "DefaultLine", "content": "dicta completa sit qd\u0303 no\u0303", "wh": [244, 36], "xy": [339, 1564]}, {"type": "DefaultLine", "content": "int\u033era\u0303 \ua753uussionis initiau\u033eit.", "wh": [256, 42], "xy": [338, 1590]}, {"type": "HeadingLine", "content": "exc\u0366 daur intelligi d\u0303m in", "wh": [250, 37], "xy": [336, 1621]}, {"type": "HeadingLine", "content": "bouis truis suis aliq\u0363 te\u0303po", "wh": [251, 41], "xy": [334, 1648]}, {"type": "HeadingLine", "content": "ralite uindicare. et tam\u0303", "wh": [241, 34], "xy": [338, 1680]}, {"type": "DefaultLine", "content": "cos i\u0303tr uasa houesta \u204a liti", "wh": [243, 44], "xy": [337, 1708]}, {"type": "DefaultLine", "content": "lia ha\u0303ere.", "wh": [116, 51], "xy": [339, 1739]}], "wh": [284, 1236], "xy": [318, 547]}, {"type": "MainZone", "lines": [{"type": "DefaultLine", "content": "omnis ppls  tecu\u0303 interram", "wh": [373, 57], "xy": [608, 1137]}], "wh": [406, 1245], "xy": [596, 540]}, {"type": "MainZone", "lines": [{"type": "HeadingLine", "content": "tem moysi serui", "wh": [230, 56], "xy": [609, 819]}, {"type": "DefaultLine", "content": "bunt terram.", "wh": [111, 36], "xy": [609, 1183]}, {"type": "DefaultLine", "content": "bo filuis israei.", "wh": [224, 63], "xy": [606, 1219]}, {"type": "DefaultLine", "content": "calcauerit uesti", "wh": [240, 61], "xy": [606, 1279]}, {"type": "DefaultLine", "content": "gum pedis ues", "wh": [233, 63], "xy": [606, 1337]}, {"type": "DefaultLine", "content": "tri uob\u0303 t\u0363dam. Si", "wh": [238, 56], "xy": [605, 1399]}, {"type": "DefaultLine", "content": "ego sum ilit \u204a minister mens", "wh": [236, 37], "xy": [608, 1446]}, {"type": "DefaultLine", "content": "cut locutus sum", "wh": [224, 52], "xy": [609, 1485]}, {"type": "DefaultLine", "content": "\u00b6 Rab\u033e. leraluiturde", "wh": [158, 40], "xy": [687, 1528]}, {"type": "DefaultLine", "content": "serta \u204a inina.\u204ac\u0303. \u204a alibi. mul", "wh": [236, 34], "xy": [612, 1557]}, {"type": "DefaultLine", "content": "moysi adeserto \u204a", "wh": [231, 46], "xy": [609, 1581]}, {"type": "DefaultLine", "content": "ti ulu deserte mag q\u0363m eius", "wh": [229, 30], "xy": [609, 1618]}, {"type": "DefaultLine", "content": "lbano usq\uf1ac ad flu", "wh": [245, 54], "xy": [608, 1637]}, {"type": "DefaultLine", "content": "que habet uirum.", "wh": [156, 29], "xy": [609, 1679]}, {"type": "DefaultLine", "content": "uium magnum", "wh": [234, 46], "xy": [608, 1698]}], "wh": [280, 1236], "xy": [601, 545]}, {"type": "MainZone", "lines": [{"type": "DefaultLine", "content": "t fac", "wh": [80, 60], "xy": [767, 542]}, {"type": "DefaultLine", "content": "OR. Nunc ergo exurgen\u1de4", "wh": [319, 60], "xy": [865, 532]}, {"type": "DefaultLine", "content": "tum", "wh": [81, 59], "xy": [767, 593]}, {"type": "DefaultLine", "content": "transiordanem hune \u204a c\u0303. ui", "wh": [310, 38], "xy": [866, 578]}, {"type": "DefaultLine", "content": "de quomodo muuster moy", "wh": [309, 40], "xy": [863, 604]}, {"type": "DefaultLine", "content": "est", "wh": [66, 56], "xy": [769, 651]}, {"type": "DefaultLine", "content": "si fuerit ihesus filius dei cu\u0303", "wh": [307, 42], "xy": [864, 632]}, {"type": "DefaultLine", "content": "uenit plenitudo temporis", "wh": [303, 41], "xy": [862, 659]}, {"type": "DefaultLine", "content": "post", "wh": [70, 55], "xy": [771, 707]}, {"type": "DefaultLine", "content": "misit deus filium suum fac", "wh": [315, 39], "xy": [863, 690]}, {"type": "HeadingLine", "content": "tum ex muliere factum sub", "wh": [305, 39], "xy": [863, 717]}, {"type": "DefaultLine", "content": "lege. quia factus est suble", "wh": [312, 39], "xy": [863, 746]}, {"type": "HeadingLine", "content": "mor", "wh": [72, 53], "xy": [771, 768]}, {"type": "DefaultLine", "content": "ge\u0303 moysi. factus est minister", "wh": [317, 41], "xy": [862, 775]}, {"type": "DefaultLine", "content": "moysi.", "wh": [78, 39], "xy": [864, 805]}, {"type": "DefaultLine", "content": "moysi.", "wh": [305, 38], "xy": [865, 805]}, {"type": "HeadingLine", "content": "\u00b6 ih\u0303m dei filium.", "wh": [179, 35], "xy": [968, 851]}, {"type": "DefaultLine", "content": "dei ut loqueretur donnus ad iosue filiu\u0303", "wh": [583, 56], "xy": [601, 874]}, {"type": "DefaultLine", "content": "q\u0365 quia n\u0303 uenit souiere segem s\uf1ac ad implere.", "wh": [485, 36], "xy": [677, 913]}, {"type": "DefaultLine", "content": "nun minustrum moysi. et diceret ei.", "wh": [550, 64], "xy": [606, 927]}, {"type": "DefaultLine", "content": "\u00b6 Lex q\u0303 inq\u0363m pedagogis fuit. \u00b6 Sed\u0303i litteram. uiuit pu\u0303", "wh": [490, 51], "xy": [679, 972]}, {"type": "DefaultLine", "content": "Loyses seruus meus mortuus est", "wh": [533, 65], "xy": [618, 1014]}, {"type": "DefaultLine", "content": "surge et transi iordanem istum tu et", "wh": [550, 61], "xy": [607, 1073]}, {"type": "DefaultLine", "content": "\u00b6 uiuentium u\u0303i\u0303 mitet qm\u0303 ip\u0303t posside\u0303", "wh": [316, 40], "xy": [860, 1113]}, {"type": "DefaultLine", "content": "cu\u0303 interraM \u00b6 non noytes. q\u0303 mor", "wh": [386, 47], "xy": [808, 1138]}, {"type": "HeadingLine", "content": "quam ego da", "wh": [212, 47], "xy": [977, 1168]}, {"type": "DefaultLine", "content": "q\u0303 qui sursum e\u0303st.", "wh": [177, 33], "xy": [979, 1207]}, {"type": "DefaultLine", "content": "inem locuimn quem", "wh": [302, 51], "xy": [882, 1228]}, {"type": "DefaultLine", "content": "OR. Omne\u0303 locu\u0303 qu\u0303etu\u0303q ascen", "wh": [313, 43], "xy": [870, 1292]}, {"type": "DefaultLine", "content": "deritis uestigiis pelu\u0303 ur\u0303o\ua775 uob\u033e", "wh": [304, 39], "xy": [866, 1327]}, {"type": "InterlinearLine", "content": "\u00b6ubi", "wh": [54, 33], "xy": [786, 1383]}, {"type": "DefaultLine", "content": "dabo \u204ac\u0303. littera legishium posita", "wh": [313, 38], "xy": [867, 1356]}, {"type": "DefaultLine", "content": "e\u0303 \u204a deorsum n\u0303 g\u0366 ascenclit qui litt\u033eam", "wh": [327, 39], "xy": [867, 1384]}, {"type": "DefaultLine", "content": "legis sequitur sz si ascenderis ad", "wh": [306, 37], "xy": [866, 1413]}, {"type": "DefaultLine", "content": "sp\u0303m de litt\u0303a. ascendis locum exte", "wh": [315, 40], "xy": [865, 1440]}, {"type": "DefaultLine", "content": "sum \ua759\u0303 adeo in heclitate accipies.", "wh": [320, 44], "xy": [861, 1467]}, {"type": "DefaultLine", "content": "Sieium in hus q\u0303 scripta su\u0303t in", "wh": [321, 42], "xy": [858, 1497]}, {"type": "DefaultLine", "content": "telligas formas ee celestium \u204a q\u0303ra", "wh": [331, 46], "xy": [861, 1523]}, {"type": "DefaultLine", "content": "q\u0303 suisu\u0303 su\u0303t. ubi xp\u0303c e\u0303indext\u033ea dei se", "wh": [328, 41], "xy": [865, 1555]}, {"type": "DefaultLine", "content": "deus. tunc illu\u0303 iccu\u0303 in heditate as", "wh": [320, 41], "xy": [865, 1586]}, {"type": "DefaultLine", "content": "tipies. qr ubi xp\u0303e e\u0303 ibi \u204a ministe", "wh": [324, 40], "xy": [867, 1616]}, {"type": "DefaultLine", "content": "ei\ua770. Sig\u0366 usc\uf1ac ad p\u0303m sedente\u0303 i\u0303dexta\u0303 di\u0303", "wh": [335, 44], "xy": [867, 1644]}, {"type": "DefaultLine", "content": "\ua751uenis fide u\u0365tute p\u033eitate \u204a ar uesti", "wh": [324, 39], "xy": [866, 1677]}, {"type": "DefaultLine", "content": "gus q\u0303 lauit i\u0142r x\u0366 adiu\u0303 locu\u0303 accesse.", "wh": [334, 42], "xy": [867, 1706]}, {"type": "DefaultLine", "content": "uefficiaris heres d\u033ei s\uf1ac coheres \ua753p\u0303i.", "wh": [288, 53], "xy": [816, 1736]}], "wh": [508, 1258], "xy": [710, 525]}], "alto": "f1-p-005-vue-2.xml", "wh": [1680, 2500]}]}