{"cote": "Cluny. Mus\u00e9e d'Art et d'Arch\u00e9ologie, Mns 40", "ark_portail": "ark:/43093/mdatad9f019c66efd84a82ce2348e283d0013efbdee1b", "langue": "lat", "start_year": 1401, "stop_year": "", "notes_scopecontent": "", "manifest_url": "https://api.irht.cnrs.fr/ark:/63955/fxh01ldzhie0/manifest.json", "qid_data": "https://data.biblissima.fr/entity/Q205029", "files": [{"zones": [{"type": "MarginTextZone", "lines": [{"type": "DefaultLine", "content": "uliulin luln leun lin lu len liali sinlinlialia lindu linlin in lin sialin dnsinsioud  linsn st n lenlenlea sonlindrast en le a le lnalaliui linsinlie inlin liulialiuliu liuliu\u0303 iu liuliululiuliululiu liu lu siulu lin diuiulas", "wh": [3042, 114], "xy": [287, 374]}, {"type": "DefaultLine", "content": "nenura ea tuan tena e e a ua ar a ta a sa a e tia a\u0303ti\u0303n at it rt it pt uat rt na a e aa a a u a t i u pitn i pmnn npamimummmnmn pumn pmm m pumt", "wh": [2456, 123], "xy": [876, 255]}, {"type": "DefaultLine", "content": "us ioieioia is is nio io 2ori erora ro es eieo2o SOC1 or u8Sao8 don18", "wh": [2455, 93], "xy": [877, 324]}], "wh": [2599, 249], "xy": [175, 223]}, {"type": "MainZone", "lines": [{"type": "DefaultLine", "content": "\ua751EEEEEPRSS SESSERS EREEESEBEEAESLE AEIREAESUS", "wh": [2491, 102], "xy": [216, 445]}, {"type": "DefaultLine", "content": "q\u0303testodeot p\u0303rtzade ro\u0303es docrrocqe iles nadopao", "wh": [2675, 92], "xy": [255, 525]}, {"type": "DefaultLine", "content": "es e tes ze\u204aoas\u0303e eo \u204ats seg\u0303o \u204a prdlsoss gosas odsdo qae sesooee", "wh": [2394, 75], "xy": [304, 711]}, {"type": "DefaultLine", "content": "EBE PETEEEESEESEESESB EOESG ESSEESSS EVEES", "wh": [2371, 79], "xy": [332, 872]}, {"type": "DefaultLine", "content": "\u204a saepe eos fltreees eles elee rsoqoea  qn", "wh": [2358, 81], "xy": [338, 906]}, {"type": "DefaultLine", "content": "qaa do Eo q\u0303q\u0303teq\u0303 \u204aade o re\u0303 flo s eoeopio \u204aoo\u0303poeldo\u0303a", "wh": [2388, 83], "xy": [316, 1008]}, {"type": "DefaultLine", "content": "eqr e fio \u204aale q ad \u204as\ua751s so \u204alic\u204aegb pt+", "wh": [2359, 82], "xy": [347, 1040]}, {"type": "DefaultLine", "content": "Eoq\ua751\u204a \u204aeeicselae \u204a e te soseao as eeeoa od+boeoeso cabor pe", "wh": [2387, 80], "xy": [318, 1102]}, {"type": "DefaultLine", "content": "as q e \ua751 esaa\u0303s qsesa cero \u204as psos e q\u0303 aose s ca \u204as cel ca c\u0327cos eacedebe", "wh": [2397, 116], "xy": [318, 1174]}], "wh": [2389, 823], "xy": [338, 464]}, {"type": "MainZone", "lines": [{"type": "DefaultLine", "content": "D SSSEERS", "wh": [1019, 97], "xy": [343, 1362]}, {"type": "DefaultLine", "content": "o\u0303eceadeos e oopododea", "wh": [2352, 93], "xy": [339, 1533]}, {"type": "DefaultLine", "content": "E\ua751 D a\u204a eosEREEEEEEE", "wh": [1717, 68], "xy": [977, 1715]}, {"type": "DefaultLine", "content": "spsdoeeeet at o \ua751lopodb", "wh": [2351, 97], "xy": [347, 1860]}, {"type": "DefaultLine", "content": "e nes\u0303 essi l no beqe\u204aages anis e aedu\u0303 eseaq +Eb", "wh": [2357, 110], "xy": [347, 2033]}], "wh": [2381, 834], "xy": [342, 1329]}], "alto": "f0-vue-1-avec-reglet.xml", "wh": [3333, 2500]}, {"zones": [{"type": "MainZone", "lines": [{"type": "DefaultLine", "content": "EEEESSSS SESSEES EBSEEESSESESOMSESTE ARIREUS", "wh": [2341, 100], "xy": [366, 449]}, {"type": "DefaultLine", "content": "\u204ades\u204aoo p\u0365e egaof psssdogsgo pide ross \u204a oabde pep", "wh": [2357, 73], "xy": [347, 541]}, {"type": "DefaultLine", "content": "o \u204a pes ae \u204aoce\u0303pe eo ttf sag\u0303o\u0303 \u204a pedssoss tede qdsos oopesode", "wh": [2387, 72], "xy": [313, 711]}, {"type": "DefaultLine", "content": "o\u0303\u204a to\u0303 asses\u0303 spe ass roe qeges eoqeyoeeoee", "wh": [1895, 66], "xy": [806, 883]}, {"type": "DefaultLine", "content": "dto oq aeoeageospua", "wh": [2366, 95], "xy": [336, 993]}, {"type": "DefaultLine", "content": "eEceete qo soa eeecaodceto", "wh": [2379, 84], "xy": [326, 1101]}, {"type": "DefaultLine", "content": "s is \u204ae \ua751 esne s pceasertoae p\u0303sos e s pese \u204a ceie \u204ab apel cae\u0327 eos ea cedebee", "wh": [2380, 122], "xy": [330, 1173]}, {"type": "DefaultLine", "content": "te e \u204a Ee fco e beres \u204a egsle p\u0303lo\u0303 as e\u0303q\u0303eeaes", "wh": [1770, 75], "xy": [929, 1048]}], "wh": [2396, 840], "xy": [334, 447]}, {"type": "MainZone", "lines": [{"type": "DefaultLine", "content": "DEES", "wh": [1028, 99], "xy": [347, 1363]}, {"type": "DefaultLine", "content": "os et opodotadedeed", "wh": [2337, 91], "xy": [354, 1532]}, {"type": "DefaultLine", "content": "SEEEEEAOERDEEEEIEEI", "wh": [2326, 86], "xy": [362, 1701]}, {"type": "DefaultLine", "content": "EsaLEEEEEEATES EEE++ps", "wh": [2326, 85], "xy": [367, 1867]}, {"type": "DefaultLine", "content": "o nes esial n be\u204aohs ahidensao edeeeego oe", "wh": [2328, 102], "xy": [366, 2033]}], "wh": [2357, 847], "xy": [361, 1319]}], "alto": "f1-vue-1.xml", "wh": [3333, 2500]}, {"zones": [{"type": "MainZone", "lines": [{"type": "DefaultLine", "content": "es oee euee dee ee coee eco e g", "wh": [2391, 146], "xy": [309, 1098]}], "wh": [2429, 826], "xy": [310, 435]}], "alto": "f2-vue-2.xml", "wh": [3333, 2500]}, {"zones": [{"type": "MainZone", "lines": [{"type": "DefaultLine", "content": "\ua751 en\u0303 dr\u1dd1 u\u0142 q\u0303rer\u033e u\u0142 retin\u0303e pos\u1e9cone\u0303 an", "wh": [549, 60], "xy": [241, 235]}, {"type": "DefaultLine", "content": "\ua751 fcm abbis sine \ua76fsci\u0303a \ua76fuentus admit", "wh": [544, 48], "xy": [244, 276]}, {"type": "DefaultLine", "content": "tant\u1dd1 \ua753fessio alicin\ua770 iur\u0364 ad mo\u0303ast\u0364 in\u0303 \ua751ti", "wh": [554, 50], "xy": [238, 307]}, {"type": "DefaultLine", "content": "nentis an sine ai\u0303o possidentis po\u0303t amitti", "wh": [555, 46], "xy": [241, 341]}, {"type": "DefaultLine", "content": "pos\u1e9cio cu\u0303 \ua757s \ua751aliu\u0303 possidet anpo\u0303t \ua751der\u0364", "wh": [554, 55], "xy": [241, 372]}, {"type": "DefaultLine", "content": "pos\u1e9conez se nesc\u0327iente \ua759 licz abbas solus", "wh": [546, 48], "xy": [239, 408]}, {"type": "DefaultLine", "content": "poss age \ua753 mo\u0303ast\u033eio no\u0303 tu\u0303 ip\u0303e solus possid\uf1ac", "wh": [562, 51], "xy": [239, 437]}, {"type": "DefaultLine", "content": "s\u0303 cu\u0303 \ua76fuentu \u204a \ua759 u\u0365 \ua76fstat pos\u1e9cone\uf1ac fuisse", "wh": [554, 49], "xy": [242, 468]}, {"type": "DefaultLine", "content": "iniqus\u0303 \u204a dolosa\uf1ac cassu d\uf1ac indicari \ua76fc quid", "wh": [571, 50], "xy": [241, 496]}, {"type": "DefaultLine", "content": "pit ex ea. de reli do. cu\u0303 dilctus. \u1e9cm inno.", "wh": [571, 49], "xy": [237, 528]}, {"type": "DefaultLine", "content": "\u00b6An \ua751 solinone\u0303 census sca\uf1ac a sac\u033e dote q\u0303rat\u1dd1", "wh": [580, 54], "xy": [227, 557]}, {"type": "DefaultLine", "content": "pos\u1e9co \u204a \ua759 pos\u1e9c\u033eo no\u0303 est alicui molent\u0364 anf\u033eenda", "wh": [577, 51], "xy": [239, 588]}, {"type": "DefaultLine", "content": "\u204a \ua759 pos\u1e9cone\u0303 sua\u0303 cu\u0303 armis \ua757s \u204a\u0303 defend\u033ee\u033e", "wh": [550, 48], "xy": [244, 622]}, {"type": "DefaultLine", "content": "po\u0303t. de censi. sig\u0365ficauit. \u1e9cm iunoc.", "wh": [487, 48], "xy": [244, 653]}, {"type": "DefaultLine", "content": "\u00b6e \u0127 \u204a \u204a an pos\u1e9cio sine ai\u0303o \u204a ei\ua770 \ua757 possidet", "wh": [560, 53], "xy": [235, 681]}, {"type": "DefaultLine", "content": "sc\u0303ia amittant\u1dd1 \u204a an lic\uf1ac alicui recu\ua751ar\u0364 in", "wh": [559, 47], "xy": [246, 714]}, {"type": "DefaultLine", "content": "\ua76ftinenti \u204a\u0303 cu\u0303 armis pos\u1e9c one\u0303 a\u0303missa\uf1ac ibide\u0303.", "wh": [573, 50], "xy": [246, 742]}, {"type": "DefaultLine", "content": "\u204a de postula. p\u0303la. bone .ii.\u1e9c .e.e sua cu\u0303 exto\u0303e", "wh": [574, 50], "xy": [239, 775]}, {"type": "DefaultLine", "content": "\u00b6 An licet alici defende\u033e pos\u1e9co\u0303e\uf1ac/.s. de ap .s.", "wh": [591, 54], "xy": [224, 804]}, {"type": "DefaultLine", "content": "de efftu\u0303.u. sieps.\u204a .s\u0303.de sen.ex.s.si. i\u0303 m\u0142tis u\u033e", "wh": [581, 53], "xy": [236, 835]}, {"type": "DefaultLine", "content": "\u00b6Antisnia lata pos\u1e9corio licite app\u0142\u0142at\u1dd1 \u204a antal", "wh": [585, 57], "xy": [235, 864]}, {"type": "DefaultLine", "content": "sn\u0303ia diffinic\u0303ia dicat\u1dd1. de nom o\ua751. n\u0303i .c. p\u0142t.", "wh": [572, 53], "xy": [241, 900]}, {"type": "DefaultLine", "content": "\u204a de resti.spo\u0142. cu\u0303 ad se .\u1e9c.B. \ua76f fugitinu\u0303 dn\u0303o", "wh": [566, 51], "xy": [242, 935]}, {"type": "DefaultLine", "content": "\u00b6An pos\u1e9co qrat\u1dd1 \ua751 mo\u0303achu\u0303 \u204a\u0303/ ignonti.s\u0303.tide", "wh": [593, 56], "xy": [228, 968]}, {"type": "DefaultLine", "content": "mo\u0303acho .u\u033e. an qc \ua757d. erit p\u033escripto \ua759 pos\u1e9cio", "wh": [577, 52], "xy": [240, 1003]}, {"type": "DefaultLine", "content": "\u00b6 O sme pos\u1e9cone no\u0303 cur qua\u0303 \ua757s tenet \ua751 se nu\u0303\ua759\u0363", "wh": [612, 59], "xy": [230, 1032]}, {"type": "DefaultLine", "content": "amittit\u1dd1 sme sci\u0303a \u204a ai\u0303o possidentis/ \u204a \ua759 talis", "wh": [563, 52], "xy": [246, 1068]}, {"type": "DefaultLine", "content": "po\u0142\u1e9co no\u0303 n\u0365 afcs de trib\uf1ac moi\u0303s \ua751dit\u1dd1. de o\u1e9c or", "wh": [568, 54], "xy": [247, 1098]}, {"type": "DefaultLine", "content": "horente. \u1e9cmquno.  cognitone e aufenda", "wh": [577, 50], "xy": [247, 1130]}, {"type": "DefaultLine", "content": "\u00b6pospo ne\u0303 m sie ca\u0303e/ de ma. \u204a obe. \u204a t\u033e.iiii\u0363. \u1e9c.e.", "wh": [604, 56], "xy": [227, 1158]}, {"type": "DefaultLine", "content": "\u00b6 Qind pet\uf1ac qui \ua751 indice\u0303 e\u0303 p\u0365nat\ua770 pos\u1e9cone. de", "wh": [593, 57], "xy": [225, 1190]}, {"type": "DefaultLine", "content": "\ua753ai. a. ex insi. \u1e9cm .e. \u0366 \ua753bare \ua759 nec ni nec", "wh": [571, 54], "xy": [251, 1224]}, {"type": "DefaultLine", "content": "Anpscrabens tenet\u1dd1 ciam n\u0368 ptario posside", "wh": [587, 56], "xy": [236, 1253]}, {"type": "DefaultLine", "content": "at de p\u0303scrip. dde q\u0363r ta .\u1e9cie. et e u\u0142 retine de", "wh": [591, 54], "xy": [244, 1284]}, {"type": "DefaultLine", "content": "Qn\u0303 \ua757s ideat\u1dd1 pos\u1e9cone\uf1ac am\u0363 res.spo o\u0142i ii.", "wh": [551, 55], "xy": [242, 1315]}, {"type": "DefaultLine", "content": "Ano pot q\u0365s \ua753bar \u0364 \ua751 centu\u0303 annos se possedisse", "wh": [602, 58], "xy": [235, 1344]}, {"type": "DefaultLine", "content": "\u204a an \ua751 nstrm\u0303 \ua753bet\u1dd1 pos\u1e9cio. de p\u033escp\u0365. cu\u0303 nobis.", "wh": [596, 56], "xy": [245, 1377]}, {"type": "DefaultLine", "content": "\u00b6Qmid \ua753dest \ua753bare solam pos\u1e9cone\uf1ac. de resti.spo.", "wh": [605, 58], "xy": [236, 1408]}, {"type": "DefaultLine", "content": "sepe . \u1e9cm inno. \u204a fitit ut iuddeat\u1dd1 neglecta pos", "wh": [599, 57], "xy": [243, 1441]}, {"type": "DefaultLine", "content": "\u00b6E ntu tep\ua770 sus / sessio. de e\u0142t.qrela\uf1ac. \u1e9cmien", "wh": [598, 61], "xy": [238, 1470]}, {"type": "DefaultLine", "content": "\u00b6\ua758 sme \ua76fphensione pos\u1e9cois rei dniu\uf1ac tnsferat\u1dd1", "wh": [617, 62], "xy": [236, 1499]}, {"type": "DefaultLine", "content": "ut sine traditone pos\u1e9co ac\ua757rat\u1dd1. de \ua753ba. in", "wh": [585, 52], "xy": [249, 1536]}, {"type": "DefaultLine", "content": "p\u0363sem\u1e9c .e. \u204ade \ua76fsnis.ni. de frurtib\uf1ac post.li.9.", "wh": [610, 55], "xy": [245, 1563]}, {"type": "DefaultLine", "content": "\u00b6 Hone fidei pos\u1e9cor tenet\u1dd1/ \ua751ceptis.de of del.", "wh": [608, 53], "xy": [230, 1597]}, {"type": "DefaultLine", "content": "su\ua751 q\u0303onu\u0303 \u1e9cure. Com\u0303s restituit \ua757 ad eu\u0303", "wh": [575, 52], "xy": [247, 1628]}, {"type": "DefaultLine", "content": "\u00b6 M ale fideiant possor \ua751ue\u0303isse \ua753bant\u1dd1. derest\u0366", "wh": [611, 60], "xy": [240, 1655]}, {"type": "DefaultLine", "content": "ppo\u0142 g\u0363uis. o gesto\ua775 plus ual\uf1ac pos\u1e9cio \ua759 u\u033eitas", "wh": [594, 57], "xy": [245, 1691]}, {"type": "DefaultLine", "content": "\u00b6 ad uolore\uf1ac / de resti.spo. m\u0142ris. \u1e9cm. Inno.", "wh": [596, 54], "xy": [233, 1724]}, {"type": "DefaultLine", "content": "\u00b6De bone u\u0142 malefidei pos\u1e9core/ anfacit fruc.", "wh": [619, 55], "xy": [234, 1755]}, {"type": "DefaultLine", "content": "tus suos anuasent q\u0303 facit \ua759\u0363 diu ab\u033e ecca tos", "wh": [601, 51], "xy": [250, 1786]}, {"type": "DefaultLine", "content": "Terat\u1dd1 ^ an ei solue\u0303tes lib\u033eent\u1dd1. \u204a de mltis si\u0142ib\uf1ac", "wh": [575, 47], "xy": [253, 1817]}, {"type": "DefaultLine", "content": "Sc\u0303o .c. in so\u0303i\u0303s. \u204a de elc. nit\u0127.\u1e9cm .e.", "wh": [490, 47], "xy": [248, 1848]}, {"type": "DefaultLine", "content": "\u00b6 O\uf1ac co\u0303modu\u0303 pos\u1e9coi\u0303s \u204a o\u0303i\u0303s fructus e\u033e ueri dm\u0303", "wh": [611, 57], "xy": [233, 1876]}, {"type": "DefaultLine", "content": "\u204a si no\u0303 possidet si n\u0142\u0142s ali est in pos\u1e9cone u\u0142e\u1de4\u1de4", "wh": [591, 55], "xy": [249, 1908]}, {"type": "DefaultLine", "content": "a\uf1ac male fidei. setus sibona fide. de e\u0142t. cu", "wh": [585, 52], "xy": [254, 1940]}, {"type": "DefaultLine", "content": "mana. \u1e9c\u0365m .e. An subdelgati u\u0142 miores", "wh": [580, 73], "xy": [258, 1969]}], "wh": [637, 1789], "xy": [212, 238]}, {"type": "MainZone", "lines": [{"type": "DefaultLine", "content": "nidices possint in pos\u1e9cone nutte co\u0303rle\uf1ac", "wh": [528, 56], "xy": [914, 230]}, {"type": "DefaultLine", "content": "de ofior.cu\u0303 ab. \u1e9cni inno. e alieno possit", "wh": [542, 53], "xy": [915, 268]}, {"type": "DefaultLine", "content": "\u00b6An is \ua757 pos\u1e9cone noi\u0303e possid\uf1ac \ua753 illa regue", "wh": [566, 55], "xy": [890, 301]}, {"type": "DefaultLine", "content": "niri \u204a antali eiecc\u0303o de pos\u1e9cone dn\u0303s uide", "wh": [555, 52], "xy": [917, 334]}, {"type": "DefaultLine", "content": "at\u1dd1 exp\u0142sus \u204a de \ua757b\uf1acda\uf1ac .q. t\u0363c \u0127. ut lic\u0364.", "wh": [534, 50], "xy": [918, 369]}, {"type": "DefaultLine", "content": "no\u0303 .\ua76f. qm\u0303. \u1e9cmie. Su\u0142 alt\u033eius reidonate", "wh": [536, 46], "xy": [921, 403]}, {"type": "DefaultLine", "content": "Anect\u0303e u\u0142 decie\u0303 pos\u1e9co\u0303e\uf1ac ingredi \ua757s po\u0303t", "wh": [533, 48], "xy": [914, 433]}, {"type": "DefaultLine", "content": "aue\u0303te \ua753pria. \u204a sire\u0303 do nata\u0303 donatari\ua770", "wh": [523, 47], "xy": [922, 463]}, {"type": "DefaultLine", "content": "occupau\u033eit auc\u0303te \ua753pria an pot\u033eit cogi ad", "wh": [542, 49], "xy": [919, 492]}, {"type": "DefaultLine", "content": "restito\u0303ne\uf1ac pos\u1e9coms \ua751 int dcm ude ii.", "wh": [531, 47], "xy": [920, 525]}, {"type": "DefaultLine", "content": "utise s\u0142 directu\u0303. de p\u0365m\u0142. pastora\u0142.\u1e9c .e.", "wh": [543, 46], "xy": [919, 554]}, {"type": "DefaultLine", "content": "an uidet\u1dd1 t\u0365nsire pos\u1e9c\u033eo re\ua775 hi \u1d48 ditarm\u0303", "wh": [540, 49], "xy": [919, 585]}, {"type": "DefaultLine", "content": "n\u0365 cu\u0303 sing\u0142a\ua775 re\ua775 e pos\u1e9co app\u033ehensa \u204a si", "wh": [525, 46], "xy": [922, 616]}, {"type": "DefaultLine", "content": "int\u1dd1 duos e \ua76ftento\u0303 de pos\u1e9cone ut qr ut\u0366q\uf1ac", "wh": [545, 45], "xy": [921, 646]}, {"type": "DefaultLine", "content": "dicit se possider\u1d48 u\u0142 uent\u0364 dicit se posside", "wh": [545, 51], "xy": [922, 673]}, {"type": "DefaultLine", "content": "a\uf1ac ut\u1dd1\ua759\uf1ac festinat pos\u1e9cone\u0303 acci\ua751e \u204a e ibi sor-", "wh": [563, 50], "xy": [922, 705]}, {"type": "DefaultLine", "content": "te timor armo\ua775 \ua757d fanet iudex \u204a quid\u0303 si", "wh": [558, 48], "xy": [920, 736]}, {"type": "DefaultLine", "content": "dubitat\u1dd1 ne si\u0142 cu\u0303 armis \ua76fcurra\u0303t ad pos", "wh": [542, 48], "xy": [923, 766]}, {"type": "DefaultLine", "content": "sessione\u0303 accipienda\uf1ac \u204a \ua757dsic\u033etu\u0303 e\u0303 \ua759pot", "wh": [526, 53], "xy": [924, 796]}, {"type": "DefaultLine", "content": "asm\u0303 p\u033eue\u0303ire \u204a si sem\u0142 \ua757s fuit a iudice u\u033ebo", "wh": [559, 54], "xy": [924, 827]}, {"type": "DefaultLine", "content": "u\u0142 fc\u0303o\u0303 \ua753\u0127i\u0303tus ingredi pos\u1e9con\u0303e an lic\uf1ac illi\u0303", "wh": [553, 53], "xy": [926, 862]}, {"type": "DefaultLine", "content": "u\u0142 a lii\u0303pos\u1e9cone\u0303 acci\ua751e quonsq\uf1ac lis fuerit", "wh": [539, 51], "xy": [924, 896]}, {"type": "DefaultLine", "content": "sopita \u204a qualit\u033e lis hui\ua770 so\ua751iet\u1dd1. aneiquise", "wh": [537, 51], "xy": [926, 929]}, {"type": "DefaultLine", "content": "Sic\u0303it possider\u033e incubit \ua753baco an pos\u1e9co p\u0303be", "wh": [559, 54], "xy": [925, 959]}, {"type": "DefaultLine", "content": "de uacantis u\u0142 ei\ua770 bona sicite occapent\u1dd1 \ua759\u0363", "wh": [538, 45], "xy": [925, 997]}, {"type": "DefaultLine", "content": "res p\u0303\u033ebende uacantis n\u0142 no\u0303 uaca\u0303tis no\u0303i\u0303e", "wh": [535, 46], "xy": [925, 1028]}, {"type": "DefaultLine", "content": "ee\u0303te possidet\u1dd1 de \ua753ba. in p\u033esentia. \u1e9cmie.", "wh": [535, 48], "xy": [927, 1057]}, {"type": "DefaultLine", "content": "An \ua751 i\u0303nestitura u\u0142 aliu\u0303 \ua76ftractu\u0303 sine tra", "wh": [549, 50], "xy": [921, 1086]}, {"type": "DefaultLine", "content": "d itone pos\u1e9co t\u0303asferat\u1dd1. de hiis que fi. a", "wh": [535, 51], "xy": [924, 1115]}, {"type": "DefaultLine", "content": "ma .\ua751.ca\u0303. exore.s\u0303.e. \u204a .s.t. de i\u0303estitura", "wh": [533, 49], "xy": [930, 1146]}, {"type": "DefaultLine", "content": "\u204a .i\u0303.t.px .u\u033e. qualit\u033e et qn\u0303. etis. Aniura di", "wh": [541, 53], "xy": [928, 1177]}, {"type": "DefaultLine", "content": "\u00b6\u204aeca pos\u1e9conis \u204a \ua753prieta / cant\u1dd1 \ua753prie possi", "wh": [570, 59], "xy": [907, 1206]}, {"type": "DefaultLine", "content": "deriul qi possideri.\ua759 pospio u\u0142 q\u0363i\u0303 pos\u1e9co", "wh": [543, 50], "xy": [931, 1244]}, {"type": "DefaultLine", "content": "no\u0303 cadit i\u0303 uire n\u0365 ro\u0303ne actus n\u0142 ex\u033eticii.", "wh": [544, 48], "xy": [932, 1275]}, {"type": "DefaultLine", "content": "\u204a qualit\u1dd1 dr\u1dd1\u0363 quis e\u0303e\u0303 in pos\u1e9cone n\u0142 qi\u0303 eli-", "wh": [551, 50], "xy": [926, 1303]}, {"type": "DefaultLine", "content": "gendi mi\u0366 di\u0303onis u\u0142 alicu\ua770 iuris u\u0142 \u1e9cui-", "wh": [553, 54], "xy": [936, 1333]}, {"type": "DefaultLine", "content": "tutis an\u0303e pos. \u204a \ua753prie. cora\u0303 eode\u0303 indice", "wh": [557, 49], "xy": [935, 1368]}, {"type": "DefaultLine", "content": "sint tractande \u204a qualit\u033e \u204a au uale\u0303t lr\u0303e", "wh": [535, 47], "xy": [934, 1400]}, {"type": "DefaultLine", "content": "ad diu\u0303sos iudices impetrate su\ua751 ca\u0303", "wh": [526, 48], "xy": [932, 1432]}, {"type": "DefaultLine", "content": "pos \u204a \ua753prie /\u204a quar\u0366 pos\u1e9co dr\u0363 momentu\u0303", "wh": [532, 52], "xy": [937, 1462]}, {"type": "DefaultLine", "content": "e ti.ci\u1e9cm\ua76fino. \u204a petitorio naleat si\u0142", "wh": [540, 50], "xy": [936, 1490]}, {"type": "DefaultLine", "content": "\u00b6 An \u204a qn pos\u1e9corior/ agi an i\u0303 \ua753mi\u0303ciatoe", "wh": [554, 55], "xy": [923, 1519]}, {"type": "DefaultLine", "content": "p\u0303mitit\u1dd1 pos\u1e9co d\uf1ac in execucoe p\u0303nal\uf1ac \ua753prie", "wh": [554, 55], "xy": [937, 1550]}, {"type": "DefaultLine", "content": "tus \u204a an sina lata su\ua751pos. possit postmod", "wh": [578, 58], "xy": [936, 1582]}, {"type": "DefaultLine", "content": "agi petitoio n\u0142 e\ua76ft\u0303. eit. cu\u0303 Di\u0142cus.", "wh": [475, 50], "xy": [938, 1618]}, {"type": "DefaultLine", "content": "\u00b6 An pos\u1e9co possit den i sub \ua76fditone anqui", "wh": [579, 59], "xy": [917, 1644]}, {"type": "DefaultLine", "content": "possidet \ua751 colonui\u0303 aliu\u0303 ue que\u0303tu\u0303q\uf1ac illo", "wh": [542, 56], "xy": [935, 1680]}, {"type": "DefaultLine", "content": "expulso dn\u0303s \u204a ignorens \ua751dit pos\u1e9cone\u0303", "wh": [534, 53], "xy": [944, 1714]}, {"type": "DefaultLine", "content": "\ua759 possidins \ua751 se ip\u0303m no\u0303 \ua751dit po\u1e9c\u1e9cone\uf1ac", "wh": [536, 51], "xy": [943, 1746]}, {"type": "DefaultLine", "content": "n\u0365 ip\u0303e sit ex pulsus u\u0142 reu\u033etens no\u0303 fu\u033eit", "wh": [539, 49], "xy": [940, 1778]}, {"type": "DefaultLine", "content": "admissus u\u0142 suspitat\ua770 fu\u033eit se possere", "wh": [542, 51], "xy": [942, 1807]}, {"type": "DefaultLine", "content": "pel\u0142i. Quidsi pospone\u0303 que\u0303 \ua751me possideo", "wh": [556, 54], "xy": [940, 1838]}, {"type": "DefaultLine", "content": "tucla possides qn possides tm\u0303 n\u0363alit\u033e", "wh": [540, 53], "xy": [940, 1870]}, {"type": "DefaultLine", "content": "qn\u0303 nauiralit\u1dd1 \u204a cruilit\u033e s sessione\u0303 amissa\uf1ac", "wh": [556, 54], "xy": [940, 1899]}, {"type": "DefaultLine", "content": "\u00b6 It\u0303e nu\u0303\ua757d e\u033e m\u0365 licctu\u0303 pos / \ua751 uim recu\ua751ar\u0364", "wh": [564, 49], "xy": [929, 1932]}, {"type": "DefaultLine", "content": "abeo \ua759 clam possone\uf1ac met occripanie", "wh": [530, 66], "xy": [945, 1960]}], "wh": [597, 1797], "xy": [896, 222]}, {"type": "MainZone", "lines": [{"type": "DefaultLine", "content": "\u204a aliqn\u0303 post ponenda.uiii.q.i\u0303 sc\u0365pturis", "wh": [530, 56], "xy": [1827, 225]}, {"type": "DefaultLine", "content": "exemplu\u0303 ibi de ysaia \u204a de ierenna.", "wh": [468, 49], "xy": [1830, 264]}, {"type": "DefaultLine", "content": "\u00b6 Ite sicut ntili\ua770 est hr\u0303e prudentiores \ua759\u0363", "wh": [550, 57], "xy": [1812, 293]}, {"type": "DefaultLine", "content": "por mosiores amicos. sic ntilior e uerior", "wh": [543, 49], "xy": [1833, 329]}, {"type": "DefaultLine", "content": "\ua759\u0363 di\u1e9ctior \u1e9cmo u\u0142 p\u033edicato .d. xxxuiii. se", "wh": [540, 50], "xy": [1831, 361]}, {"type": "DefaultLine", "content": "dulo. s p\u033edicato\u0303 suscitat spn\u0303alit\u033e mortuos", "wh": [560, 52], "xy": [1830, 392]}, {"type": "DefaultLine", "content": "item uiii.q.i. olim.  \u204a scia irre p\u0303\u0127en", "wh": [550, 50], "xy": [1823, 424]}, {"type": "DefaultLine", "content": "\u00b6 \ua758 p\u0303dicator d\uf1ace\u0303e i\u0303 nita sibi\u0142. e.q. o\ua751tet", "wh": [536, 50], "xy": [1821, 456]}, {"type": "DefaultLine", "content": ".d.xxxui. s. ecce. d .xxxuiii.c.i.", "wh": [443, 48], "xy": [1830, 487]}, {"type": "DefaultLine", "content": "\u00b6 Ite p\u0303dicator pur\ua770 d\uf1ace\u0303e\u0303 a pi\u0303co. dil qd e\u1d48", "wh": [547, 54], "xy": [1824, 514]}, {"type": "DefaultLine", "content": "\u0127\u033e. \u204a .c. cn\u0303 exandiero . \u204a.d. xxxu. sexto. i\u0303 fu", "wh": [542, 47], "xy": [1834, 549]}, {"type": "DefaultLine", "content": "\u00b6 Ite\u0303 frnctu\u0303 x\u0365 no\u0303 suu\u0303 d\uf1ac intende\u033e .uiii.q.\u0365.", "wh": [556, 49], "xy": [1810, 579]}, {"type": "DefaultLine", "content": "olim. \u204a .c. inscripturis. p\u0303s entiu\u0303 d\uf1ac \u1e9cmone\u0303", "wh": [546, 48], "xy": [1831, 609]}, {"type": "DefaultLine", "content": "\u00b6 Ite\u0303 p\u0303m capacitate\u0303 audi formare uiii. q", "wh": [560, 49], "xy": [1822, 640]}, {"type": "DefaultLine", "content": ".i. o\ua751t\uf1ac. p\u033e cultu\u0303 x\u0365 ampliando n\u0368 pp aliud ul\u0142a", "wh": [574, 52], "xy": [1827, 670]}, {"type": "DefaultLine", "content": "\u00b6 Ite\u0303 n\u0363 \ua753\ua751 d\uf1ac ro\u0303ne mentiri .xxii.q.ii p\u0365mu\u0303.", "wh": [571, 48], "xy": [1814, 704]}, {"type": "DefaultLine", "content": "\u00b6 Ite p\u033edicator d\uf1ac e\u0303e\u0303 actinus \u204a \ua76fte\u0303platiuus", "wh": [569, 47], "xy": [1814, 734]}, {"type": "DefaultLine", "content": "\u204a no\u0303 desno sensu s\uf1ac il\u0142a doce\u033e que didicit", "wh": [534, 49], "xy": [1834, 764]}, {"type": "DefaultLine", "content": ".d.xxxui. si\ua757s nu\u0142t. u\u0142 detraccionem", "wh": [529, 47], "xy": [1830, 797]}, {"type": "DefaultLine", "content": "\u00b6te n p\ua751 emusatione\uf1ac/ alio\ua775 a recta p\u0303di", "wh": [558, 51], "xy": [1812, 828]}, {"type": "DefaultLine", "content": "caco\u0303is intento\u0303ne recede\u033e d\uf1ac.S.xlii.scim\ua770.", "wh": [561, 51], "xy": [1825, 859]}, {"type": "DefaultLine", "content": "\u00b6 O\ua775 p\u033edicator ad utilitate\u0303 pp\u0142i p\u033edicans \ua76f", "wh": [568, 55], "xy": [1821, 890]}, {"type": "DefaultLine", "content": "sequit\u1dd1 a deo nberiore\u0303 gr\u0303am.xui.\ua757 .i. ren\u033e", "wh": [545, 55], "xy": [1834, 922]}, {"type": "DefaultLine", "content": "timini. s religiosus u\u0142 ali\ua770 n\u0365 ro\u0303ne p\u033elato\u0303is", "wh": [541, 53], "xy": [1836, 956]}, {"type": "DefaultLine", "content": "\u00b6 O nl\u0142s  aut \ua751 ep\u0303m n\u0142 pp\u0303m licenciat\u1dd1 nec", "wh": [559, 49], "xy": [1812, 989]}, {"type": "DefaultLine", "content": "sait\ua770 nec m\u0142r qntuu\ua76fq\uf1ac docta \u204a sc\u0303a d\uf1ac p\u033edi", "wh": [540, 51], "xy": [1835, 1018]}, {"type": "DefaultLine", "content": "care .x ui.q.i. adicim\ua770. .d . xxiii. m\u0142r. dehr\u0303ti.", "wh": [554, 51], "xy": [1838, 1049]}, {"type": "DefaultLine", "content": "ex \ua76f\u0365cam\ua770 .i. \u204a .c. cn\u0303 ex i\u0303nmeto. \u204a .c. sicut .ii.", "wh": [515, 45], "xy": [1840, 1083]}, {"type": "DefaultLine", "content": "\u00b6 Ite qui p\u0303dicatore\u0303 u\u033eitatis \ua76ftristat in", "wh": [544, 49], "xy": [1818, 1112]}, {"type": "DefaultLine", "content": "xp\u0303m pectat .xi.q.iii. \ua757ni\u0303q\uf1ac \ua76ftristauerit.", "wh": [545, 52], "xy": [1831, 1142]}, {"type": "DefaultLine", "content": "\u00b6 O nniciosi p\u0303dicatoris \u1e9cmo no\u0303 e \ua76fte\u0303pne\u0303d\ua770", "wh": [555, 52], "xy": [1819, 1175]}, {"type": "DefaultLine", "content": "\ua759 sicut lexuna \ua751 cuere hudu\u0303 fluens", "wh": [537, 47], "xy": [1837, 1210]}, {"type": "DefaultLine", "content": "sauat \u204a no\u0303 sauat\u1dd1. sic bona docirma \ua751", "wh": [532, 43], "xy": [1836, 1242]}, {"type": "DefaultLine", "content": "ma\u0142u\u0303 doctore\u0303 ai\u0303as crede\u0303tiu\u0303 apccis lauat.", "wh": [551, 44], "xy": [1839, 1271]}, {"type": "DefaultLine", "content": ".d.lxxxiii.s. n\u0142to. s c\u0303ator qui alios issmmi", "wh": [552, 45], "xy": [1833, 1300]}, {"type": "DefaultLine", "content": "\u00b6O ifelixe p\u033edi / nando ip\u0303e tene brosus", "wh": [566, 49], "xy": [1817, 1329]}, {"type": "DefaultLine", "content": "\u204a re\ua753bus effict\u1dd1. de pe. di ii.c. fiero\u0303i.", "wh": [454, 45], "xy": [1828, 1361]}, {"type": "DefaultLine", "content": "\u00b6Ite p\u0303dicator bn\u0303 docendo \u204a male niuendo", "wh": [567, 54], "xy": [1811, 1388]}, {"type": "DefaultLine", "content": "deu\u0303 instruit qualit\u033e en\u0303 debeat \ua76fde\u0303pnar", "wh": [552, 53], "xy": [1831, 1420]}, {"type": "DefaultLine", "content": ".d.xl. m\u0142ti. Qres qui ab auditorib\uf1ac no\u0303", "wh": [536, 51], "xy": [1837, 1455]}, {"type": "DefaultLine", "content": "\u00b6 Q p\u0303dicato int\u0142\u0142igunt\u1dd1 / no\u0303 audientiu\u0303", "wh": [545, 49], "xy": [1827, 1489]}, {"type": "DefaultLine", "content": "utlitate\u0303 s\uf1ac sna\u0303 ostentatione\u0303 q\u0303ru\u0303t. d.", "wh": [528, 50], "xy": [1838, 1520]}, {"type": "DefaultLine", "content": "x\u0142iii .s. parit\u1dd1. p\u0303 pdicat \ua757 pan\ua751e xp\u0303m \ua751in", "wh": [570, 56], "xy": [1837, 1550]}, {"type": "DefaultLine", "content": "\u00b6Q i\u0303 \ua76fueient\u1dd1 guinentre \u204a rubentib\uf1ac", "wh": [562, 53], "xy": [1821, 1587]}, {"type": "DefaultLine", "content": "unctis a\u0303mi\u0303tiat. d.xxx u. ecce.", "wh": [429, 46], "xy": [1840, 1621]}, {"type": "DefaultLine", "content": "\u00b6 Ite q arrogant\u033e \u204a cu\u0303 fastu n\u0303mui\u0303tiat .d.", "wh": [543, 56], "xy": [1828, 1648]}, {"type": "DefaultLine", "content": "p\u0142oi \u0127 \u0127t. qsas i\u0303miscet / qr i\u0303 nno ore", "wh": [535, 53], "xy": [1835, 1681]}, {"type": "DefaultLine", "content": "\u00b6 Ite quifabu cn\u0303 ionis laudib\uf1ac se xp\u0303i lau", "wh": [567, 56], "xy": [1824, 1710]}, {"type": "DefaultLine", "content": "des no\u0303 \ua76fparin\u0303t\u1dd1 .d. lxxxui. cu\u0303 m\u0142ta.", "wh": [472, 50], "xy": [1838, 1743]}, {"type": "DefaultLine", "content": "\u00b6O\uf1ac p\u0303diatorib\uf1ac i\u0303 su\u0303ptib\uf1ac est \ua753uidend.", "wh": [551, 56], "xy": [1827, 1772]}, {"type": "DefaultLine", "content": "xu\u0303i. q.i. ap\u0142itis.  coi\u0303s excel\u0142it statum", "wh": [546, 52], "xy": [1833, 1807]}, {"type": "DefaultLine", "content": "\u00b6 Q officiu\u0303 p\u0303dica \ua76fce\u0303p\u0142atois. de remi\u0303.", "wh": [560, 56], "xy": [1828, 1836]}, {"type": "DefaultLine", "content": "ntu\u0303 pride\uf1ac. exe\u0303 p\u0142u\u0303 ibi\u0127s deieremia.", "wh": [531, 50], "xy": [1841, 1869]}, {"type": "DefaultLine", "content": "\u00b6M p\u0303dicatorib\uf1ac licet ab exco\u0303itatis ele", "wh": [543, 53], "xy": [1837, 1897]}, {"type": "DefaultLine", "content": "tosina recipe qn\u0303 ip\u0303as p\u0303dica\u0303t si no\u0303 ualet", "wh": [553, 53], "xy": [1844, 1927]}, {"type": "DefaultLine", "content": "at sustentari. de semex. cu\u0303 nolutate.", "wh": [545, 67], "xy": [1843, 1960]}], "wh": [611, 1785], "xy": [1799, 233]}, {"type": "text", "lines": [{"type": "DefaultLine", "content": "CCxxi", "wh": [128, 67], "xy": [2367, 126]}], "wh": [0, 0], "xy": [0, 0]}, {"type": "MainZone", "lines": [{"type": "DefaultLine", "content": "\u00b6 \ua759 n\u0303o sufficit alicui dit\u033ee \ua759 sit\u0303 a deo miss\ua770", "wh": [598, 68], "xy": [2463, 206]}, {"type": "DefaultLine", "content": "ad p\u033edditand\u0303 n\u0365 hoc ostendat. de hr\u0364ti.", "wh": [539, 54], "xy": [2496, 250]}, {"type": "DefaultLine", "content": "cu\u0303 ex i\u0303nmieto. \u00b6 p\u033edicaco\u0303is \ua753pria auc\u0303te", "wh": [546, 51], "xy": [2494, 284]}, {"type": "DefaultLine", "content": "\u00b6 Ite u\u0142\u0142s ospm  sibi assimat \u204a si \ua76ft\u0303fec\u033eit", "wh": [566, 55], "xy": [2467, 314]}, {"type": "DefaultLine", "content": "exto\u0303itet\u1dd1 \u204a n\u0365 se correx\u0303it asia \u204a\u0303 pena pm\u0303at\u1dd1", "wh": [566, 56], "xy": [2487, 345]}, {"type": "DefaultLine", "content": "eiti. exroi\u0303cam\ua770 .s. qr n\u0363o. star\u033e s\uf1ac tm\u0303 lras suas", "wh": [574, 53], "xy": [2482, 379]}, {"type": "DefaultLine", "content": "\u00b6 Ite q\u0303stiarii no\u0303 debet p\u0303di/ expon\u0303e .e\u0303x. de pe.", "wh": [591, 53], "xy": [2464, 412]}, {"type": "DefaultLine", "content": "\u204a recu\u0303 ex eo.\u204a de hr\u0303ti. ut offm\u0303. li. ui.", "wh": [492, 50], "xy": [2479, 444]}, {"type": "DefaultLine", "content": "\u00b6Qr p\u0303dicantes paganis sicite ip\u0303o\ua775 cibis quos", "wh": [584, 57], "xy": [2462, 471]}, {"type": "DefaultLine", "content": "appom\u0303t possu\u0303t uti \u1e9cnata te\u0303po\ua775 qlitate. de", "wh": [566, 55], "xy": [2485, 505]}, {"type": "DefaultLine", "content": "uide. \u204a sara. \ua759\u0303sit. e oido in m\u0142ts e\u0303 p\u0365mi\u0142iat\ua770", "wh": [570, 55], "xy": [2483, 536]}, {"type": "DefaultLine", "content": "\u00b6 E p\u0303dicato\ua775 frm\u0303/.de exces. p\u033esa. nimis .ii.", "wh": [581, 52], "xy": [2467, 570]}, {"type": "DefaultLine", "content": "\u00b6An possit \ua757s in alt\u033eius dioc\u0303. p\u0303dicar\u1d48 pomifi", "wh": [577, 53], "xy": [2468, 599]}, {"type": "DefaultLine", "content": "calib\uf1ac insigniis uti \u204a si\u0142ia fac\u033ee. de nsupal.", "wh": [549, 50], "xy": [2485, 632]}, {"type": "DefaultLine", "content": "extua\ua775. \u204a .ui.q.iii. scriptu\u0303.  possint.", "wh": [485, 47], "xy": [2485, 664]}, {"type": "DefaultLine", "content": "\u00b6 uidde \u204a\u0303 sup\u0127 u\u033e.i. po\u0303itu\u0303 qui  tores mitte", "wh": [592, 54], "xy": [2462, 692]}, {"type": "DefaultLine", "content": "\u00b6Q ecc\u0303a ad infideles po\u0303t p\u033edica / ac eos ut", "wh": [570, 52], "xy": [2470, 723]}, {"type": "DefaultLine", "content": "p\u0303dicatores recipiant \ua76fpeller\u0303. de noto. \ua759si.", "wh": [573, 52], "xy": [2480, 754]}, {"type": "DefaultLine", "content": "\u1e9cm imo. admitt\u033ee ad p\u033edicand il\u0142os qui", "wh": [569, 52], "xy": [2480, 787]}, {"type": "DefaultLine", "content": "\u00b6 AAndebem\ua770 / uessent p\u033edicar\u033e lege\u0303 mosayca\uf1ac", "wh": [573, 52], "xy": [2462, 820]}, {"type": "DefaultLine", "content": "u\u0142 legeni matometi. ibide\uf1ac. \u00b6ubi \u204a cuiette", "wh": [572, 50], "xy": [2479, 853]}, {"type": "DefaultLine", "content": "\u00b6 Qui possint p\u033edicar\u033e u\u0142 no\u0303 et/ applicabint\u1dd1", "wh": [596, 54], "xy": [2451, 884]}, {"type": "DefaultLine", "content": "que falsus p\u0303dicator ae\ua757rit/ \u204a \ua757s possit dar\u0364", "wh": [566, 52], "xy": [2484, 918]}, {"type": "DefaultLine", "content": "sicentia\u0303 exneo p\u0303dicandi u\u0142 alia hi\ua770 facie\u0303di", "wh": [557, 46], "xy": [2482, 954]}, {"type": "DefaultLine", "content": "xcix. d. \u1e9cm .xcii. dic .ii. \u204a xui.q.. adicim\ua770. de", "wh": [580, 48], "xy": [2479, 984]}, {"type": "DefaultLine", "content": "nideis. \ua759\u0363sit. de hi\u0364ci. cu\u0303 exi\u0303meto. \u204a .c. sunt", "wh": [577, 46], "xy": [2481, 1017]}, {"type": "DefaultLine", "content": ".iiII. \u204a .c.exto\u0303icam\ua770 .i. \u1e9c\u0303m inno. \u204a alios. \u204a i\u0303gie.ti.", "wh": [587, 48], "xy": [2478, 1047]}, {"type": "DefaultLine", "content": "\u00b6 An omi u\u033ebo p\u033edicatonis sit credend\u033e.d. tide", "wh": [595, 47], "xy": [2460, 1077]}, {"type": "DefaultLine", "content": "doctrina.e.u\u033e. sati ad quos ap\u0142o\ua775 p\u033edicato\u0303", "wh": [598, 50], "xy": [2470, 1107]}, {"type": "DefaultLine", "content": "\u00b6 An il\u0142i sint excu no\u0303 pueit .xxxuii. d. n\u0303o oi\u0303s.", "wh": [596, 47], "xy": [2458, 1140]}, {"type": "DefaultLine", "content": "al e\u0303 sub .s. u\u0142to. p\u033ephatio bt\u0303e uirgi\u0303s noue\u0303", "wh": [571, 48], "xy": [2480, 1172]}, {"type": "DefaultLine", "content": "Refatio. \ua758\u033e anti\ua757o\ua775 p\u033efato\u0303ib\uf1ac \ua751 \ua76fciliu\u0303\u0303", "wh": [536, 48], "xy": [2521, 1205]}, {"type": "DefaultLine", "content": "addita e. d. lxx. sco\ua775. in fi. es noue sunt", "wh": [532, 46], "xy": [2525, 1238]}, {"type": "DefaultLine", "content": "\u00b6 \ua758 excepta bt\u0303e nu\u0303 gnus p\u0303faco\u0303e q\u0303 \ua751 cir culu\u0303", "wh": [595, 48], "xy": [2458, 1268]}, {"type": "DefaultLine", "content": "anni decantant\u1dd1. de .9.d.a. i\u0303ienim\ua770.", "wh": [495, 43], "xy": [2483, 1300]}, {"type": "DefaultLine", "content": "\u00b6 \ua758 ante p\u033efacione\u0303 ido\u0303 sm su\u0303 cordda dr\u1dd1 ut tu\u0303c", "wh": [605, 49], "xy": [2457, 1326]}, {"type": "DefaultLine", "content": "p\u0303tipue mente\u0303 ad deu\u0303 erig\u033ee \ua751leb\u033es moneat\u1dd1", "wh": [592, 48], "xy": [2485, 1356]}, {"type": "DefaultLine", "content": ".e.d. qn\u0303 au\u0303t. \u00b6s d\uf1ac dici qn\u0303 ex tp\u0303s u\u0142 de bta\u0303", "wh": [570, 47], "xy": [2479, 1385]}, {"type": "DefaultLine", "content": "\u00b6An p\u0303fato\u0303 \ua753p\u0365a / uirgi\u0303e u\u0142 de sco\u0303 spu\u0303 u\u0142 de", "wh": [584, 54], "xy": [2465, 1415]}, {"type": "DefaultLine", "content": "sca\u0303 cruce missa cantat\u1dd1. decel. mis. \ua76fciliu\u0303.", "wh": [545, 49], "xy": [2474, 1449]}, {"type": "DefaultLine", "content": "Refectus. Anasma p\u033efecti appl\u0142et\u1dd1 ues", "wh": [530, 51], "xy": [2513, 1478]}, {"type": "DefaultLine", "content": "supplicet\u1dd1. de u\u0303nt\u033e. rest. ex lr\u0303is. \u1e9cm inno.", "wh": [549, 52], "xy": [2513, 1509]}, {"type": "DefaultLine", "content": "An p\u0303fectus po\u0303t aliqne\u0303 ad tp\u0303s n\u0142 ppetuo \ua753 hi-", "wh": [583, 53], "xy": [2479, 1541]}, {"type": "DefaultLine", "content": "\u1e9cer\u0303. de of.se. \ua759 tnssa. \u1e9cmie.  ansit p\u033efiue\u0303d\ua770", "wh": [608, 55], "xy": [2474, 1571]}, {"type": "DefaultLine", "content": "Refiiendus seu \ua753mone\u0303d\ua770/ marorib\uf1ac mi", "wh": [533, 53], "xy": [2528, 1607]}, {"type": "DefaultLine", "content": "norib\uf1ac indign\ua770 \u204a an qui dign\ua770 e\u033e unadi", "wh": [531, 52], "xy": [2534, 1640]}, {"type": "DefaultLine", "content": "enitate reputet\u1dd1 dign\ua770 ad alia u\u0142 egt\u0303. u\u0142", "wh": [591, 51], "xy": [2464, 1673]}, {"type": "DefaultLine", "content": "ei possit ali\ua757d obiti .s\u0303. de e\u0303lo.s.iiii.u. an \ua753", "wh": [583, 48], "xy": [2477, 1705]}, {"type": "DefaultLine", "content": "moueat\u1dd1. or. \u204a .ti. de eta. \u204a quali. su\u0303t m\u0142ta", "wh": [595, 49], "xy": [2469, 1733]}, {"type": "DefaultLine", "content": "\u00b6 Si d\u0364 te\u0303po. que faciu\u0303t ad hu\u0303c .ti. de p\u033efic\u0327i", "wh": [611, 55], "xy": [2459, 1759]}, {"type": "DefaultLine", "content": "endo se u \ua753moriendo. Esuend\ua770 teneat\u1dd1 \ua753de\u033e", "wh": [576, 52], "xy": [2486, 1792]}, {"type": "DefaultLine", "content": "\u00b6 An p\u0303ficiend\ua770 sen \ua753mo crime\u0303 fuu\u0303 u\u0142 impe", "wh": [598, 52], "xy": [2466, 1826]}, {"type": "DefaultLine", "content": "Dimentu\u0303.i\u0303. ti. de \ua753ditone .u\u033e. an \ua753mone\u0303d\ua770", "wh": [588, 52], "xy": [2477, 1856]}, {"type": "DefaultLine", "content": "\u00b6 De pc\u0303co ei\ua770 qui in \ua753moco\u0303ne sua suu\u0303 impedri", "wh": [601, 51], "xy": [2465, 1889]}, {"type": "DefaultLine", "content": "mentu\u0303 tatuit .s\u0303. ti. de Dispen .s. iii.u. an epi\u0303.", "wh": [591, 47], "xy": [2478, 1921]}, {"type": "DefaultLine", "content": "\u00b6 \ua758 \ua753mouendus e quis de mn\u0303ori ad maius", "wh": [615, 65], "xy": [2460, 1949]}], "wh": [639, 1791], "xy": [2449, 214]}], "alto": "f3-vue-3.xml", "wh": [3333, 2500]}]}